{
	"application_count": 17,
	"completed_application_count": 16,
	"total_task_count": 141,
	"finish_time": 9618.69,
	"completed_task_count": 140,
	"completed_tasks": [
		{
			"task_name": "APP_0_Input_Layer_0",
			"total_task_id": 0,
			"application_id": 0,
			"task_id": 0,
			"data_in": 16,
			"data_out": 19,
			"can_offload": 0,
			"chosen_node_id": 2,
			"source_node_id": 2,
			"chosen_node_type": "mobile",
			"input_upload_start_time": 0,
			"input_upload_finish_time": 0,
			"process_start_time": 1,
			"process_finish_time": 251,
			"output_upload_start_time": 0,
			"output_upload_finish_time": 0,
			"parents": [
			],
			"parent_upload_windows": {
			}
		},
		{
			"task_name": "APP_0_Inner_Layer_0:0",
			"total_task_id": 1,
			"application_id": 0,
			"task_id": 1,
			"data_in": 19,
			"data_out": 34,
			"can_offload": 1,
			"chosen_node_id": 4,
			"source_node_id": 2,
			"chosen_node_type": "edge",
			"input_upload_start_time": 252,
			"input_upload_finish_time": 388.667,
			"process_start_time": 388.667,
			"process_finish_time": 522,
			"output_upload_start_time": 0,
			"output_upload_finish_time": 0,
			"parents": [
				"APP_0_Input_Layer_0"
			],
			"parent_upload_windows": {
				"2": [
					["252", "388.667"]
				]
			}
		},
		{
			"task_name": "APP_1_Input_Layer_0",
			"total_task_id": 6,
			"application_id": 1,
			"task_id": 0,
			"data_in": 41,
			"data_out": 3,
			"can_offload": 1,
			"chosen_node_id": 4,
			"source_node_id": 2,
			"chosen_node_type": "edge",
			"input_upload_start_time": 0,
			"input_upload_finish_time": 0,
			"process_start_time": 389.667,
			"process_finish_time": 589.667,
			"output_upload_start_time": 0,
			"output_upload_finish_time": 0,
			"parents": [
			],
			"parent_upload_windows": {
			}
		},
		{
			"task_name": "APP_1_Inner_Layer_0:0",
			"total_task_id": 7,
			"application_id": 1,
			"task_id": 1,
			"data_in": 9,
			"data_out": 8,
			"can_offload": 1,
			"chosen_node_id": 4,
			"source_node_id": 2,
			"chosen_node_type": "edge",
			"input_upload_start_time": 0,
			"input_upload_finish_time": 0,
			"process_start_time": 590.667,
			"process_finish_time": 857.333,
			"output_upload_start_time": 0,
			"output_upload_finish_time": 0,
			"parents": [
				"APP_1_Input_Layer_0"
			],
			"parent_upload_windows": {
			}
		},
		{
			"task_name": "APP_1_Inner_Layer_1:3",
			"total_task_id": 11,
			"application_id": 1,
			"task_id": 5,
			"data_in": 24,
			"data_out": 42,
			"can_offload": 1,
			"chosen_node_id": 3,
			"source_node_id": 2,
			"chosen_node_type": "edge",
			"input_upload_start_time": 858.333,
			"input_upload_finish_time": 876.146,
			"process_start_time": 876.146,
			"process_finish_time": 942.812,
			"output_upload_start_time": 0,
			"output_upload_finish_time": 0,
			"parents": [
				"APP_1_Inner_Layer_0:0"
			],
			"parent_upload_windows": {
				"4": [
					["858.333", "876.146"]
				]
			}
		},
		{
			"task_name": "APP_0_Inner_Layer_0:1",
			"total_task_id": 2,
			"application_id": 0,
			"task_id": 2,
			"data_in": 40,
			"data_out": 14,
			"can_offload": 1,
			"chosen_node_id": 3,
			"source_node_id": 2,
			"chosen_node_type": "edge",
			"input_upload_start_time": 252,
			"input_upload_finish_time": 388.667,
			"process_start_time": 388.667,
			"process_finish_time": 988.667,
			"output_upload_start_time": 0,
			"output_upload_finish_time": 0,
			"parents": [
				"APP_0_Input_Layer_0"
			],
			"parent_upload_windows": {
				"2": [
					["252", "388.667"]
				]
			}
		},
		{
			"task_name": "APP_2_Input_Layer_0",
			"total_task_id": 15,
			"application_id": 2,
			"task_id": 0,
			"data_in": 43,
			"data_out": 47,
			"can_offload": 1,
			"chosen_node_id": 1,
			"source_node_id": 2,
			"chosen_node_type": "edge",
			"input_upload_start_time": 0,
			"input_upload_finish_time": 0,
			"process_start_time": 591.667,
			"process_finish_time": 991.667,
			"output_upload_start_time": 0,
			"output_upload_finish_time": 0,
			"parents": [
			],
			"parent_upload_windows": {
			}
		},
		{
			"task_name": "APP_1_Inner_Layer_1:1",
			"total_task_id": 9,
			"application_id": 1,
			"task_id": 3,
			"data_in": 15,
			"data_out": 33,
			"can_offload": 1,
			"chosen_node_id": 4,
			"source_node_id": 2,
			"chosen_node_type": "edge",
			"input_upload_start_time": 0,
			"input_upload_finish_time": 0,
			"process_start_time": 858.333,
			"process_finish_time": 1058.33,
			"output_upload_start_time": 0,
			"output_upload_finish_time": 0,
			"parents": [
				"APP_1_Inner_Layer_0:0"
			],
			"parent_upload_windows": {
			}
		},
		{
			"task_name": "APP_2_Inner_Layer_0:0",
			"total_task_id": 16,
			"application_id": 2,
			"task_id": 1,
			"data_in": 31,
			"data_out": 18,
			"can_offload": 1,
			"chosen_node_id": 1,
			"source_node_id": 2,
			"chosen_node_type": "edge",
			"input_upload_start_time": 0,
			"input_upload_finish_time": 0,
			"process_start_time": 992.667,
			"process_finish_time": 1126,
			"output_upload_start_time": 0,
			"output_upload_finish_time": 0,
			"parents": [
				"APP_2_Input_Layer_0"
			],
			"parent_upload_windows": {
			}
		},
		{
			"task_name": "APP_1_Inner_Layer_1:0",
			"total_task_id": 8,
			"application_id": 1,
			"task_id": 2,
			"data_in": 31,
			"data_out": 13,
			"can_offload": 1,
			"chosen_node_id": 4,
			"source_node_id": 2,
			"chosen_node_type": "edge",
			"input_upload_start_time": 0,
			"input_upload_finish_time": 0,
			"process_start_time": 858.333,
			"process_finish_time": 1325,
			"output_upload_start_time": 0,
			"output_upload_finish_time": 0,
			"parents": [
				"APP_1_Inner_Layer_0:0"
			],
			"parent_upload_windows": {
			}
		},
		{
			"task_name": "APP_1_Inner_Layer_1:2",
			"total_task_id": 10,
			"application_id": 1,
			"task_id": 4,
			"data_in": 36,
			"data_out": 35,
			"can_offload": 1,
			"chosen_node_id": 1,
			"source_node_id": 2,
			"chosen_node_type": "edge",
			"input_upload_start_time": 858.333,
			"input_upload_finish_time": 876.146,
			"process_start_time": 876.146,
			"process_finish_time": 1342.81,
			"output_upload_start_time": 0,
			"output_upload_finish_time": 0,
			"parents": [
				"APP_1_Inner_Layer_0:0"
			],
			"parent_upload_windows": {
				"4": [
					["858.333", "876.146"]
				]
			}
		},
		{
			"task_name": "APP_3_Input_Layer_0",
			"total_task_id": 20,
			"application_id": 3,
			"task_id": 0,
			"data_in": 32,
			"data_out": 41,
			"can_offload": 1,
			"chosen_node_id": 4,
			"source_node_id": 2,
			"chosen_node_type": "edge",
			"input_upload_start_time": 0,
			"input_upload_finish_time": 0,
			"process_start_time": 1059.57,
			"process_finish_time": 1392.9,
			"output_upload_start_time": 0,
			"output_upload_finish_time": 0,
			"parents": [
			],
			"parent_upload_windows": {
			}
		},
		{
			"task_name": "APP_2_Inner_Layer_0:1",
			"total_task_id": 17,
			"application_id": 2,
			"task_id": 2,
			"data_in": 39,
			"data_out": 13,
			"can_offload": 1,
			"chosen_node_id": 3,
			"source_node_id": 2,
			"chosen_node_type": "edge",
			"input_upload_start_time": 992.667,
			"input_upload_finish_time": 1048.57,
			"process_start_time": 1048.57,
			"process_finish_time": 1448.57,
			"output_upload_start_time": 0,
			"output_upload_finish_time": 0,
			"parents": [
				"APP_2_Input_Layer_0"
			],
			"parent_upload_windows": {
				"1": [
					["992.667", "1048.57"]
				]
			}
		},
		{
			"task_name": "APP_2_Inner_Layer_0:2",
			"total_task_id": 18,
			"application_id": 2,
			"task_id": 3,
			"data_in": 34,
			"data_out": 17,
			"can_offload": 1,
			"chosen_node_id": 0,
			"source_node_id": 2,
			"chosen_node_type": "cloud",
			"input_upload_start_time": 992.667,
			"input_upload_finish_time": 1058.57,
			"process_start_time": 1058.57,
			"process_finish_time": 1458.57,
			"output_upload_start_time": 0,
			"output_upload_finish_time": 0,
			"parents": [
				"APP_2_Input_Layer_0"
			],
			"parent_upload_windows": {
				"1": [
					["992.667", "1058.57"]
				]
			}
		},
		{
			"task_name": "APP_0_Inner_Layer_1:0",
			"total_task_id": 3,
			"application_id": 0,
			"task_id": 3,
			"data_in": 26,
			"data_out": 36,
			"can_offload": 1,
			"chosen_node_id": 3,
			"source_node_id": 2,
			"chosen_node_type": "edge",
			"input_upload_start_time": 523,
			"input_upload_finish_time": 566.203,
			"process_start_time": 988.667,
			"process_finish_time": 1522,
			"output_upload_start_time": 0,
			"output_upload_finish_time": 0,
			"parents": [
				"APP_0_Inner_Layer_0:1",
				"APP_0_Inner_Layer_0:0"
			],
			"parent_upload_windows": {
				"4": [
					["523", "566.203"]
				]
			}
		},
		{
			"task_name": "APP_3_Inner_Layer_0:0",
			"total_task_id": 21,
			"application_id": 3,
			"task_id": 1,
			"data_in": 9,
			"data_out": 13,
			"can_offload": 1,
			"chosen_node_id": 1,
			"source_node_id": 2,
			"chosen_node_type": "edge",
			"input_upload_start_time": 1393.9,
			"input_upload_finish_time": 1443.94,
			"process_start_time": 1443.94,
			"process_finish_time": 1643.94,
			"output_upload_start_time": 0,
			"output_upload_finish_time": 0,
			"parents": [
				"APP_3_Input_Layer_0"
			],
			"parent_upload_windows": {
				"4": [
					["1393.9", "1443.94"]
				]
			}
		},
		{
			"task_name": "APP_2_Output_Layer_0",
			"total_task_id": 19,
			"application_id": 2,
			"task_id": 4,
			"data_in": 45,
			"data_out": 9,
			"can_offload": 1,
			"chosen_node_id": 3,
			"source_node_id": 2,
			"chosen_node_type": "edge",
			"input_upload_start_time": 1459.57,
			"input_upload_finish_time": 1496.17,
			"process_start_time": 1496.17,
			"process_finish_time": 1829.5,
			"output_upload_start_time": 0,
			"output_upload_finish_time": 0,
			"parents": [
				"APP_2_Inner_Layer_0:0",
				"APP_2_Inner_Layer_0:1",
				"APP_2_Inner_Layer_0:2"
			],
			"parent_upload_windows": {
				"1": [
					["1459.57", "1487.14"]
				],
				"0": [
					["1459.57", "1496.17"]
				]
			}
		},
		{
			"task_name": "APP_4_Input_Layer_0",
			"total_task_id": 31,
			"application_id": 4,
			"task_id": 0,
			"data_in": 21,
			"data_out": 5,
			"can_offload": 1,
			"chosen_node_id": 1,
			"source_node_id": 2,
			"chosen_node_type": "edge",
			"input_upload_start_time": 0,
			"input_upload_finish_time": 0,
			"process_start_time": 1395.83,
			"process_finish_time": 1862.49,
			"output_upload_start_time": 0,
			"output_upload_finish_time": 0,
			"parents": [
			],
			"parent_upload_windows": {
			}
		},
		{
			"task_name": "APP_3_Inner_Layer_0:1",
			"total_task_id": 22,
			"application_id": 3,
			"task_id": 2,
			"data_in": 12,
			"data_out": 49,
			"can_offload": 1,
			"chosen_node_id": 0,
			"source_node_id": 2,
			"chosen_node_type": "cloud",
			"input_upload_start_time": 1393.9,
			"input_upload_finish_time": 1453.94,
			"process_start_time": 1453.94,
			"process_finish_time": 1920.6,
			"output_upload_start_time": 0,
			"output_upload_finish_time": 0,
			"parents": [
				"APP_3_Input_Layer_0"
			],
			"parent_upload_windows": {
				"4": [
					["1393.9", "1453.94"]
				]
			}
		},
		{
			"task_name": "APP_0_Inner_Layer_2:0",
			"total_task_id": 4,
			"application_id": 0,
			"task_id": 4,
			"data_in": 40,
			"data_out": 3,
			"can_offload": 1,
			"chosen_node_id": 3,
			"source_node_id": 2,
			"chosen_node_type": "edge",
			"input_upload_start_time": 0,
			"input_upload_finish_time": 0,
			"process_start_time": 1523,
			"process_finish_time": 1923,
			"output_upload_start_time": 0,
			"output_upload_finish_time": 0,
			"parents": [
				"APP_0_Inner_Layer_1:0"
			],
			"parent_upload_windows": {
			}
		},
		{
			"task_name": "APP_1_Inner_Layer_2:0",
			"total_task_id": 12,
			"application_id": 1,
			"task_id": 6,
			"data_in": 16,
			"data_out": 26,
			"can_offload": 1,
			"chosen_node_id": 4,
			"source_node_id": 2,
			"chosen_node_type": "edge",
			"input_upload_start_time": 0,
			"input_upload_finish_time": 0,
			"process_start_time": 1326,
			"process_finish_time": 1926,
			"output_upload_start_time": 0,
			"output_upload_finish_time": 0,
			"parents": [
				"APP_1_Inner_Layer_1:0"
			],
			"parent_upload_windows": {
			}
		},
		{
			"task_name": "APP_3_Inner_Layer_1:2",
			"total_task_id": 25,
			"application_id": 3,
			"task_id": 5,
			"data_in": 47,
			"data_out": 44,
			"can_offload": 1,
			"chosen_node_id": 0,
			"source_node_id": 2,
			"chosen_node_type": "cloud",
			"input_upload_start_time": 1644.94,
			"input_upload_finish_time": 1677.63,
			"process_start_time": 1677.63,
			"process_finish_time": 1944.3,
			"output_upload_start_time": 0,
			"output_upload_finish_time": 0,
			"parents": [
				"APP_3_Inner_Layer_0:0"
			],
			"parent_upload_windows": {
				"1": [
					["1644.94", "1677.63"]
				]
			}
		},
		{
			"task_name": "APP_5_Input_Layer_0",
			"total_task_id": 41,
			"application_id": 5,
			"task_id": 0,
			"data_in": 34,
			"data_out": 5,
			"can_offload": 1,
			"chosen_node_id": 0,
			"source_node_id": 2,
			"chosen_node_type": "cloud",
			"input_upload_start_time": 0,
			"input_upload_finish_time": 0,
			"process_start_time": 1678.63,
			"process_finish_time": 1945.3,
			"output_upload_start_time": 0,
			"output_upload_finish_time": 0,
			"parents": [
			],
			"parent_upload_windows": {
			}
		},
		{
			"task_name": "APP_0_Output_Layer_0",
			"total_task_id": 5,
			"application_id": 0,
			"task_id": 5,
			"data_in": 19,
			"data_out": 23,
			"can_offload": 1,
			"chosen_node_id": 3,
			"source_node_id": 2,
			"chosen_node_type": "edge",
			"input_upload_start_time": 0,
			"input_upload_finish_time": 0,
			"process_start_time": 1924,
			"process_finish_time": 1990.67,
			"output_upload_start_time": 0,
			"output_upload_finish_time": 0,
			"parents": [
				"APP_0_Inner_Layer_2:0"
			],
			"parent_upload_windows": {
			}
		},
		{
			"task_name": "APP_1_Inner_Layer_2:1",
			"total_task_id": 13,
			"application_id": 1,
			"task_id": 7,
			"data_in": 41,
			"data_out": 38,
			"can_offload": 1,
			"chosen_node_id": 4,
			"source_node_id": 2,
			"chosen_node_type": "edge",
			"input_upload_start_time": 1343.81,
			"input_upload_finish_time": 1394.83,
			"process_start_time": 1394.83,
			"process_finish_time": 1994.83,
			"output_upload_start_time": 0,
			"output_upload_finish_time": 0,
			"parents": [
				"APP_1_Inner_Layer_1:1",
				"APP_1_Inner_Layer_1:3",
				"APP_1_Inner_Layer_1:2"
			],
			"parent_upload_windows": {
				"1": [
					["1343.81", "1387.99"]
				],
				"3": [
					["1343.81", "1394.83"]
				]
			}
		},
		{
			"task_name": "APP_4_Inner_Layer_0:2",
			"total_task_id": 34,
			"application_id": 4,
			"task_id": 3,
			"data_in": 27,
			"data_out": 37,
			"can_offload": 1,
			"chosen_node_id": 3,
			"source_node_id": 2,
			"chosen_node_type": "edge",
			"input_upload_start_time": 1863.49,
			"input_upload_finish_time": 1878.38,
			"process_start_time": 1878.38,
			"process_finish_time": 2145.04,
			"output_upload_start_time": 0,
			"output_upload_finish_time": 0,
			"parents": [
				"APP_4_Input_Layer_0"
			],
			"parent_upload_windows": {
				"1": [
					["1863.49", "1878.38"]
				]
			}
		},
		{
			"task_name": "APP_3_Inner_Layer_1:1",
			"total_task_id": 24,
			"application_id": 3,
			"task_id": 4,
			"data_in": 46,
			"data_out": 7,
			"can_offload": 1,
			"chosen_node_id": 0,
			"source_node_id": 2,
			"chosen_node_type": "cloud",
			"input_upload_start_time": 0,
			"input_upload_finish_time": 0,
			"process_start_time": 1921.6,
			"process_finish_time": 2254.94,
			"output_upload_start_time": 0,
			"output_upload_finish_time": 0,
			"parents": [
				"APP_3_Inner_Layer_0:1"
			],
			"parent_upload_windows": {
			}
		},
		{
			"task_name": "APP_3_Inner_Layer_2:3",
			"total_task_id": 29,
			"application_id": 3,
			"task_id": 9,
			"data_in": 33,
			"data_out": 47,
			"can_offload": 1,
			"chosen_node_id": 0,
			"source_node_id": 2,
			"chosen_node_type": "cloud",
			"input_upload_start_time": 0,
			"input_upload_finish_time": 0,
			"process_start_time": 2255.94,
			"process_finish_time": 2322.6,
			"output_upload_start_time": 0,
			"output_upload_finish_time": 0,
			"parents": [
				"APP_3_Inner_Layer_1:2",
				"APP_3_Inner_Layer_1:1"
			],
			"parent_upload_windows": {
			}
		},
		{
			"task_name": "APP_4_Inner_Layer_0:1",
			"total_task_id": 33,
			"application_id": 4,
			"task_id": 2,
			"data_in": 49,
			"data_out": 5,
			"can_offload": 1,
			"chosen_node_id": 1,
			"source_node_id": 2,
			"chosen_node_type": "edge",
			"input_upload_start_time": 0,
			"input_upload_finish_time": 0,
			"process_start_time": 1863.49,
			"process_finish_time": 2330.16,
			"output_upload_start_time": 0,
			"output_upload_finish_time": 0,
			"parents": [
				"APP_4_Input_Layer_0"
			],
			"parent_upload_windows": {
			}
		},
		{
			"task_name": "APP_5_Inner_Layer_0:0",
			"total_task_id": 42,
			"application_id": 5,
			"task_id": 1,
			"data_in": 15,
			"data_out": 12,
			"can_offload": 1,
			"chosen_node_id": 0,
			"source_node_id": 2,
			"chosen_node_type": "cloud",
			"input_upload_start_time": 0,
			"input_upload_finish_time": 0,
			"process_start_time": 1946.3,
			"process_finish_time": 2346.3,
			"output_upload_start_time": 0,
			"output_upload_finish_time": 0,
			"parents": [
				"APP_5_Input_Layer_0"
			],
			"parent_upload_windows": {
			}
		},
		{
			"task_name": "APP_5_Inner_Layer_0:1",
			"total_task_id": 43,
			"application_id": 5,
			"task_id": 2,
			"data_in": 46,
			"data_out": 18,
			"can_offload": 1,
			"chosen_node_id": 0,
			"source_node_id": 2,
			"chosen_node_type": "cloud",
			"input_upload_start_time": 0,
			"input_upload_finish_time": 0,
			"process_start_time": 1946.3,
			"process_finish_time": 2346.3,
			"output_upload_start_time": 0,
			"output_upload_finish_time": 0,
			"parents": [
				"APP_5_Input_Layer_0"
			],
			"parent_upload_windows": {
			}
		},
		{
			"task_name": "APP_4_Inner_Layer_0:0",
			"total_task_id": 32,
			"application_id": 4,
			"task_id": 1,
			"data_in": 3,
			"data_out": 4,
			"can_offload": 1,
			"chosen_node_id": 1,
			"source_node_id": 2,
			"chosen_node_type": "edge",
			"input_upload_start_time": 0,
			"input_upload_finish_time": 0,
			"process_start_time": 1863.49,
			"process_finish_time": 2463.49,
			"output_upload_start_time": 0,
			"output_upload_finish_time": 0,
			"parents": [
				"APP_4_Input_Layer_0"
			],
			"parent_upload_windows": {
			}
		},
		{
			"task_name": "APP_3_Inner_Layer_1:0",
			"total_task_id": 23,
			"application_id": 3,
			"task_id": 3,
			"data_in": 47,
			"data_out": 17,
			"can_offload": 1,
			"chosen_node_id": 0,
			"source_node_id": 2,
			"chosen_node_type": "cloud",
			"input_upload_start_time": 0,
			"input_upload_finish_time": 0,
			"process_start_time": 1921.6,
			"process_finish_time": 2521.6,
			"output_upload_start_time": 0,
			"output_upload_finish_time": 0,
			"parents": [
				"APP_3_Inner_Layer_0:1"
			],
			"parent_upload_windows": {
			}
		},
		{
			"task_name": "APP_1_Output_Layer_0",
			"total_task_id": 14,
			"application_id": 1,
			"task_id": 8,
			"data_in": 16,
			"data_out": 46,
			"can_offload": 1,
			"chosen_node_id": 4,
			"source_node_id": 2,
			"chosen_node_type": "edge",
			"input_upload_start_time": 0,
			"input_upload_finish_time": 0,
			"process_start_time": 1995.83,
			"process_finish_time": 2529.16,
			"output_upload_start_time": 0,
			"output_upload_finish_time": 0,
			"parents": [
				"APP_1_Inner_Layer_2:0",
				"APP_1_Inner_Layer_2:1"
			],
			"parent_upload_windows": {
			}
		},
		{
			"task_name": "APP_5_Inner_Layer_1:0",
			"total_task_id": 44,
			"application_id": 5,
			"task_id": 3,
			"data_in": 42,
			"data_out": 44,
			"can_offload": 1,
			"chosen_node_id": 0,
			"source_node_id": 2,
			"chosen_node_type": "cloud",
			"input_upload_start_time": 0,
			"input_upload_finish_time": 0,
			"process_start_time": 2347.3,
			"process_finish_time": 2547.3,
			"output_upload_start_time": 0,
			"output_upload_finish_time": 0,
			"parents": [
				"APP_5_Inner_Layer_0:1",
				"APP_5_Inner_Layer_0:0"
			],
			"parent_upload_windows": {
			}
		},
		{
			"task_name": "APP_4_Inner_Layer_1:1",
			"total_task_id": 36,
			"application_id": 4,
			"task_id": 5,
			"data_in": 10,
			"data_out": 42,
			"can_offload": 1,
			"chosen_node_id": 4,
			"source_node_id": 2,
			"chosen_node_type": "edge",
			"input_upload_start_time": 2146.04,
			"input_upload_finish_time": 2345.04,
			"process_start_time": 2345.04,
			"process_finish_time": 2611.71,
			"output_upload_start_time": 0,
			"output_upload_finish_time": 0,
			"parents": [
				"APP_4_Inner_Layer_0:1",
				"APP_4_Inner_Layer_0:2"
			],
			"parent_upload_windows": {
				"3": [
					["2146.04", "2192.18"]
				],
				"1": [
					["2330.16", "2345.04"]
				]
			}
		},
		{
			"task_name": "APP_5_Inner_Layer_2:3",
			"total_task_id": 48,
			"application_id": 5,
			"task_id": 7,
			"data_in": 15,
			"data_out": 40,
			"can_offload": 1,
			"chosen_node_id": 0,
			"source_node_id": 2,
			"chosen_node_type": "cloud",
			"input_upload_start_time": 0,
			"input_upload_finish_time": 0,
			"process_start_time": 2548.3,
			"process_finish_time": 2614.97,
			"output_upload_start_time": 0,
			"output_upload_finish_time": 0,
			"parents": [
				"APP_5_Inner_Layer_1:0"
			],
			"parent_upload_windows": {
			}
		},
		{
			"task_name": "APP_3_Inner_Layer_2:2",
			"total_task_id": 28,
			"application_id": 3,
			"task_id": 8,
			"data_in": 26,
			"data_out": 47,
			"can_offload": 1,
			"chosen_node_id": 0,
			"source_node_id": 2,
			"chosen_node_type": "cloud",
			"input_upload_start_time": 0,
			"input_upload_finish_time": 0,
			"process_start_time": 2522.6,
			"process_finish_time": 2655.94,
			"output_upload_start_time": 0,
			"output_upload_finish_time": 0,
			"parents": [
				"APP_3_Inner_Layer_1:0"
			],
			"parent_upload_windows": {
			}
		},
		{
			"task_name": "APP_3_Inner_Layer_2:0",
			"total_task_id": 26,
			"application_id": 3,
			"task_id": 6,
			"data_in": 41,
			"data_out": 48,
			"can_offload": 1,
			"chosen_node_id": 0,
			"source_node_id": 2,
			"chosen_node_type": "cloud",
			"input_upload_start_time": 0,
			"input_upload_finish_time": 0,
			"process_start_time": 2255.94,
			"process_finish_time": 2722.6,
			"output_upload_start_time": 0,
			"output_upload_finish_time": 0,
			"parents": [
				"APP_3_Inner_Layer_1:1"
			],
			"parent_upload_windows": {
			}
		},
		{
			"task_name": "APP_4_Inner_Layer_1:0",
			"total_task_id": 35,
			"application_id": 4,
			"task_id": 4,
			"data_in": 34,
			"data_out": 3,
			"can_offload": 1,
			"chosen_node_id": 3,
			"source_node_id": 2,
			"chosen_node_type": "edge",
			"input_upload_start_time": 0,
			"input_upload_finish_time": 0,
			"process_start_time": 2146.04,
			"process_finish_time": 2746.04,
			"output_upload_start_time": 0,
			"output_upload_finish_time": 0,
			"parents": [
				"APP_4_Inner_Layer_0:2"
			],
			"parent_upload_windows": {
			}
		},
		{
			"task_name": "APP_6_Input_Layer_0",
			"total_task_id": 54,
			"application_id": 6,
			"task_id": 0,
			"data_in": 3,
			"data_out": 39,
			"can_offload": 0,
			"chosen_node_id": 2,
			"source_node_id": 2,
			"chosen_node_type": "mobile",
			"input_upload_start_time": 0,
			"input_upload_finish_time": 0,
			"process_start_time": 2256.94,
			"process_finish_time": 2756.94,
			"output_upload_start_time": 0,
			"output_upload_finish_time": 0,
			"parents": [
			],
			"parent_upload_windows": {
			}
		},
		{
			"task_name": "APP_7_Input_Layer_0",
			"total_task_id": 63,
			"application_id": 7,
			"task_id": 0,
			"data_in": 20,
			"data_out": 19,
			"can_offload": 1,
			"chosen_node_id": 4,
			"source_node_id": 2,
			"chosen_node_type": "edge",
			"input_upload_start_time": 0,
			"input_upload_finish_time": 0,
			"process_start_time": 2723.6,
			"process_finish_time": 2790.27,
			"output_upload_start_time": 0,
			"output_upload_finish_time": 0,
			"parents": [
			],
			"parent_upload_windows": {
			}
		},
		{
			"task_name": "APP_4_Inner_Layer_1:2",
			"total_task_id": 37,
			"application_id": 4,
			"task_id": 6,
			"data_in": 16,
			"data_out": 29,
			"can_offload": 1,
			"chosen_node_id": 1,
			"source_node_id": 2,
			"chosen_node_type": "edge",
			"input_upload_start_time": 0,
			"input_upload_finish_time": 0,
			"process_start_time": 2464.49,
			"process_finish_time": 2797.83,
			"output_upload_start_time": 0,
			"output_upload_finish_time": 0,
			"parents": [
				"APP_4_Inner_Layer_0:1",
				"APP_4_Inner_Layer_0:0"
			],
			"parent_upload_windows": {
			}
		},
		{
			"task_name": "APP_5_Inner_Layer_2:2",
			"total_task_id": 47,
			"application_id": 5,
			"task_id": 6,
			"data_in": 10,
			"data_out": 19,
			"can_offload": 1,
			"chosen_node_id": 0,
			"source_node_id": 2,
			"chosen_node_type": "cloud",
			"input_upload_start_time": 0,
			"input_upload_finish_time": 0,
			"process_start_time": 2548.3,
			"process_finish_time": 2814.97,
			"output_upload_start_time": 0,
			"output_upload_finish_time": 0,
			"parents": [
				"APP_5_Inner_Layer_1:0"
			],
			"parent_upload_windows": {
			}
		},
		{
			"task_name": "APP_3_Inner_Layer_2:1",
			"total_task_id": 27,
			"application_id": 3,
			"task_id": 7,
			"data_in": 45,
			"data_out": 7,
			"can_offload": 1,
			"chosen_node_id": 0,
			"source_node_id": 2,
			"chosen_node_type": "cloud",
			"input_upload_start_time": 0,
			"input_upload_finish_time": 0,
			"process_start_time": 2522.6,
			"process_finish_time": 2922.6,
			"output_upload_start_time": 0,
			"output_upload_finish_time": 0,
			"parents": [
				"APP_3_Inner_Layer_1:2",
				"APP_3_Inner_Layer_1:1",
				"APP_3_Inner_Layer_1:0"
			],
			"parent_upload_windows": {
			}
		},
		{
			"task_name": "APP_7_Inner_Layer_0:1",
			"total_task_id": 65,
			"application_id": 7,
			"task_id": 2,
			"data_in": 40,
			"data_out": 35,
			"can_offload": 1,
			"chosen_node_id": 4,
			"source_node_id": 2,
			"chosen_node_type": "edge",
			"input_upload_start_time": 0,
			"input_upload_finish_time": 0,
			"process_start_time": 2791.27,
			"process_finish_time": 2924.6,
			"output_upload_start_time": 0,
			"output_upload_finish_time": 0,
			"parents": [
				"APP_7_Input_Layer_0"
			],
			"parent_upload_windows": {
			}
		},
		{
			"task_name": "APP_4_Inner_Layer_2:0",
			"total_task_id": 38,
			"application_id": 4,
			"task_id": 7,
			"data_in": 15,
			"data_out": 13,
			"can_offload": 1,
			"chosen_node_id": 3,
			"source_node_id": 2,
			"chosen_node_type": "edge",
			"input_upload_start_time": 0,
			"input_upload_finish_time": 0,
			"process_start_time": 2747.04,
			"process_finish_time": 2947.04,
			"output_upload_start_time": 0,
			"output_upload_finish_time": 0,
			"parents": [
				"APP_4_Inner_Layer_1:0"
			],
			"parent_upload_windows": {
			}
		},
		{
			"task_name": "APP_5_Inner_Layer_2:1",
			"total_task_id": 46,
			"application_id": 5,
			"task_id": 5,
			"data_in": 31,
			"data_out": 47,
			"can_offload": 1,
			"chosen_node_id": 0,
			"source_node_id": 2,
			"chosen_node_type": "cloud",
			"input_upload_start_time": 0,
			"input_upload_finish_time": 0,
			"process_start_time": 2548.3,
			"process_finish_time": 3014.97,
			"output_upload_start_time": 0,
			"output_upload_finish_time": 0,
			"parents": [
				"APP_5_Inner_Layer_1:0"
			],
			"parent_upload_windows": {
			}
		},
		{
			"task_name": "APP_5_Inner_Layer_2:0",
			"total_task_id": 45,
			"application_id": 5,
			"task_id": 4,
			"data_in": 21,
			"data_out": 4,
			"can_offload": 1,
			"chosen_node_id": 0,
			"source_node_id": 2,
			"chosen_node_type": "cloud",
			"input_upload_start_time": 0,
			"input_upload_finish_time": 0,
			"process_start_time": 2548.3,
			"process_finish_time": 3014.97,
			"output_upload_start_time": 0,
			"output_upload_finish_time": 0,
			"parents": [
				"APP_5_Inner_Layer_1:0"
			],
			"parent_upload_windows": {
			}
		},
		{
			"task_name": "APP_5_Inner_Layer_3:0",
			"total_task_id": 49,
			"application_id": 5,
			"task_id": 8,
			"data_in": 42,
			"data_out": 29,
			"can_offload": 1,
			"chosen_node_id": 0,
			"source_node_id": 2,
			"chosen_node_type": "cloud",
			"input_upload_start_time": 0,
			"input_upload_finish_time": 0,
			"process_start_time": 3015.97,
			"process_finish_time": 3149.3,
			"output_upload_start_time": 0,
			"output_upload_finish_time": 0,
			"parents": [
				"APP_5_Inner_Layer_2:3",
				"APP_5_Inner_Layer_2:2",
				"APP_5_Inner_Layer_2:1",
				"APP_5_Inner_Layer_2:0"
			],
			"parent_upload_windows": {
			}
		},
		{
			"task_name": "APP_5_Inner_Layer_3:3",
			"total_task_id": 52,
			"application_id": 5,
			"task_id": 11,
			"data_in": 32,
			"data_out": 4,
			"can_offload": 1,
			"chosen_node_id": 0,
			"source_node_id": 2,
			"chosen_node_type": "cloud",
			"input_upload_start_time": 0,
			"input_upload_finish_time": 0,
			"process_start_time": 3015.97,
			"process_finish_time": 3149.3,
			"output_upload_start_time": 0,
			"output_upload_finish_time": 0,
			"parents": [
				"APP_5_Inner_Layer_2:0"
			],
			"parent_upload_windows": {
			}
		},
		{
			"task_name": "APP_7_Inner_Layer_1:1",
			"total_task_id": 67,
			"application_id": 7,
			"task_id": 4,
			"data_in": 19,
			"data_out": 17,
			"can_offload": 1,
			"chosen_node_id": 1,
			"source_node_id": 2,
			"chosen_node_type": "edge",
			"input_upload_start_time": 2925.6,
			"input_upload_finish_time": 2969.78,
			"process_start_time": 2969.78,
			"process_finish_time": 3169.78,
			"output_upload_start_time": 0,
			"output_upload_finish_time": 0,
			"parents": [
				"APP_7_Inner_Layer_0:1"
			],
			"parent_upload_windows": {
				"4": [
					["2925.6", "2969.78"]
				]
			}
		},
		{
			"task_name": "APP_3_Output_Layer_0",
			"total_task_id": 30,
			"application_id": 3,
			"task_id": 10,
			"data_in": 16,
			"data_out": 35,
			"can_offload": 1,
			"chosen_node_id": 0,
			"source_node_id": 2,
			"chosen_node_type": "cloud",
			"input_upload_start_time": 0,
			"input_upload_finish_time": 0,
			"process_start_time": 2923.6,
			"process_finish_time": 3190.27,
			"output_upload_start_time": 0,
			"output_upload_finish_time": 0,
			"parents": [
				"APP_3_Inner_Layer_2:3",
				"APP_3_Inner_Layer_2:0",
				"APP_3_Inner_Layer_2:2",
				"APP_3_Inner_Layer_2:1"
			],
			"parent_upload_windows": {
			}
		},
		{
			"task_name": "APP_5_Inner_Layer_3:2",
			"total_task_id": 51,
			"application_id": 5,
			"task_id": 10,
			"data_in": 15,
			"data_out": 49,
			"can_offload": 1,
			"chosen_node_id": 0,
			"source_node_id": 2,
			"chosen_node_type": "cloud",
			"input_upload_start_time": 0,
			"input_upload_finish_time": 0,
			"process_start_time": 3015.97,
			"process_finish_time": 3215.97,
			"output_upload_start_time": 0,
			"output_upload_finish_time": 0,
			"parents": [
				"APP_5_Inner_Layer_2:3",
				"APP_5_Inner_Layer_2:2",
				"APP_5_Inner_Layer_2:1"
			],
			"parent_upload_windows": {
			}
		},
		{
			"task_name": "APP_6_Inner_Layer_0:0",
			"total_task_id": 55,
			"application_id": 6,
			"task_id": 1,
			"data_in": 3,
			"data_out": 36,
			"can_offload": 1,
			"chosen_node_id": 4,
			"source_node_id": 2,
			"chosen_node_type": "edge",
			"input_upload_start_time": 2757.94,
			"input_upload_finish_time": 3027.94,
			"process_start_time": 3027.94,
			"process_finish_time": 3227.94,
			"output_upload_start_time": 0,
			"output_upload_finish_time": 0,
			"parents": [
				"APP_6_Input_Layer_0"
			],
			"parent_upload_windows": {
				"2": [
					["2757.94", "3027.94"]
				]
			}
		},
		{
			"task_name": "APP_5_Inner_Layer_3:1",
			"total_task_id": 50,
			"application_id": 5,
			"task_id": 9,
			"data_in": 19,
			"data_out": 19,
			"can_offload": 1,
			"chosen_node_id": 0,
			"source_node_id": 2,
			"chosen_node_type": "cloud",
			"input_upload_start_time": 0,
			"input_upload_finish_time": 0,
			"process_start_time": 3015.97,
			"process_finish_time": 3282.63,
			"output_upload_start_time": 0,
			"output_upload_finish_time": 0,
			"parents": [
				"APP_5_Inner_Layer_2:2",
				"APP_5_Inner_Layer_2:1"
			],
			"parent_upload_windows": {
			}
		},
		{
			"task_name": "APP_7_Inner_Layer_0:0",
			"total_task_id": 64,
			"application_id": 7,
			"task_id": 1,
			"data_in": 19,
			"data_out": 34,
			"can_offload": 1,
			"chosen_node_id": 3,
			"source_node_id": 2,
			"chosen_node_type": "edge",
			"input_upload_start_time": 2791.27,
			"input_upload_finish_time": 2819.83,
			"process_start_time": 2819.83,
			"process_finish_time": 3286.49,
			"output_upload_start_time": 0,
			"output_upload_finish_time": 0,
			"parents": [
				"APP_7_Input_Layer_0"
			],
			"parent_upload_windows": {
				"4": [
					["2791.27", "2819.83"]
				]
			}
		},
		{
			"task_name": "APP_6_Inner_Layer_0:1",
			"total_task_id": 56,
			"application_id": 6,
			"task_id": 2,
			"data_in": 49,
			"data_out": 7,
			"can_offload": 1,
			"chosen_node_id": 3,
			"source_node_id": 2,
			"chosen_node_type": "edge",
			"input_upload_start_time": 2757.94,
			"input_upload_finish_time": 3027.94,
			"process_start_time": 3027.94,
			"process_finish_time": 3294.6,
			"output_upload_start_time": 0,
			"output_upload_finish_time": 0,
			"parents": [
				"APP_6_Input_Layer_0"
			],
			"parent_upload_windows": {
				"2": [
					["2757.94", "3027.94"]
				]
			}
		},
		{
			"task_name": "APP_4_Inner_Layer_2:1",
			"total_task_id": 39,
			"application_id": 4,
			"task_id": 8,
			"data_in": 31,
			"data_out": 48,
			"can_offload": 1,
			"chosen_node_id": 4,
			"source_node_id": 2,
			"chosen_node_type": "edge",
			"input_upload_start_time": 2798.83,
			"input_upload_finish_time": 2837.15,
			"process_start_time": 2837.15,
			"process_finish_time": 3437.15,
			"output_upload_start_time": 0,
			"output_upload_finish_time": 0,
			"parents": [
				"APP_4_Inner_Layer_1:1",
				"APP_4_Inner_Layer_1:2"
			],
			"parent_upload_windows": {
				"1": [
					["2798.83", "2837.15"]
				]
			}
		},
		{
			"task_name": "APP_5_Output_Layer_0",
			"total_task_id": 53,
			"application_id": 5,
			"task_id": 12,
			"data_in": 27,
			"data_out": 28,
			"can_offload": 1,
			"chosen_node_id": 0,
			"source_node_id": 2,
			"chosen_node_type": "cloud",
			"input_upload_start_time": 0,
			"input_upload_finish_time": 0,
			"process_start_time": 3282.63,
			"process_finish_time": 3482.63,
			"output_upload_start_time": 0,
			"output_upload_finish_time": 0,
			"parents": [
				"APP_5_Inner_Layer_3:3",
				"APP_5_Inner_Layer_3:2",
				"APP_5_Inner_Layer_3:1",
				"APP_5_Inner_Layer_3:0"
			],
			"parent_upload_windows": {
			}
		},
		{
			"task_name": "APP_8_Input_Layer_0",
			"total_task_id": 71,
			"application_id": 8,
			"task_id": 0,
			"data_in": 16,
			"data_out": 33,
			"can_offload": 1,
			"chosen_node_id": 1,
			"source_node_id": 2,
			"chosen_node_type": "edge",
			"input_upload_start_time": 0,
			"input_upload_finish_time": 0,
			"process_start_time": 3171.78,
			"process_finish_time": 3571.78,
			"output_upload_start_time": 0,
			"output_upload_finish_time": 0,
			"parents": [
			],
			"parent_upload_windows": {
			}
		},
		{
			"task_name": "APP_9_Input_Layer_0",
			"total_task_id": 84,
			"application_id": 9,
			"task_id": 0,
			"data_in": 43,
			"data_out": 24,
			"can_offload": 1,
			"chosen_node_id": 3,
			"source_node_id": 2,
			"chosen_node_type": "edge",
			"input_upload_start_time": 0,
			"input_upload_finish_time": 0,
			"process_start_time": 3483.63,
			"process_finish_time": 3616.97,
			"output_upload_start_time": 0,
			"output_upload_finish_time": 0,
			"parents": [
			],
			"parent_upload_windows": {
			}
		},
		{
			"task_name": "APP_7_Inner_Layer_1:0",
			"total_task_id": 66,
			"application_id": 7,
			"task_id": 3,
			"data_in": 36,
			"data_out": 31,
			"can_offload": 1,
			"chosen_node_id": 3,
			"source_node_id": 2,
			"chosen_node_type": "edge",
			"input_upload_start_time": 0,
			"input_upload_finish_time": 0,
			"process_start_time": 3287.49,
			"process_finish_time": 3620.83,
			"output_upload_start_time": 0,
			"output_upload_finish_time": 0,
			"parents": [
				"APP_7_Inner_Layer_0:0"
			],
			"parent_upload_windows": {
			}
		},
		{
			"task_name": "APP_4_Output_Layer_0",
			"total_task_id": 40,
			"application_id": 4,
			"task_id": 9,
			"data_in": 33,
			"data_out": 1,
			"can_offload": 1,
			"chosen_node_id": 4,
			"source_node_id": 2,
			"chosen_node_type": "edge",
			"input_upload_start_time": 3438.15,
			"input_upload_finish_time": 3460.84,
			"process_start_time": 3460.84,
			"process_finish_time": 3727.51,
			"output_upload_start_time": 0,
			"output_upload_finish_time": 0,
			"parents": [
				"APP_4_Inner_Layer_2:0",
				"APP_4_Inner_Layer_2:1"
			],
			"parent_upload_windows": {
				"3": [
					["3438.15", "3460.84"]
				]
			}
		},
		{
			"task_name": "APP_7_Inner_Layer_2:0",
			"total_task_id": 68,
			"application_id": 7,
			"task_id": 5,
			"data_in": 33,
			"data_out": 37,
			"can_offload": 1,
			"chosen_node_id": 1,
			"source_node_id": 2,
			"chosen_node_type": "edge",
			"input_upload_start_time": 0,
			"input_upload_finish_time": 0,
			"process_start_time": 3170.78,
			"process_finish_time": 3770.78,
			"output_upload_start_time": 0,
			"output_upload_finish_time": 0,
			"parents": [
				"APP_7_Inner_Layer_1:1"
			],
			"parent_upload_windows": {
			}
		},
		{
			"task_name": "APP_6_Inner_Layer_1:0",
			"total_task_id": 57,
			"application_id": 6,
			"task_id": 3,
			"data_in": 26,
			"data_out": 1,
			"can_offload": 1,
			"chosen_node_id": 4,
			"source_node_id": 2,
			"chosen_node_type": "edge",
			"input_upload_start_time": 3294.6,
			"input_upload_finish_time": 3311.44,
			"process_start_time": 3311.44,
			"process_finish_time": 3844.77,
			"output_upload_start_time": 0,
			"output_upload_finish_time": 0,
			"parents": [
				"APP_6_Inner_Layer_0:1",
				"APP_6_Inner_Layer_0:0"
			],
			"parent_upload_windows": {
				"3": [
					["3294.6", "3311.44"]
				]
			}
		},
		{
			"task_name": "APP_11_Input_Layer_0",
			"total_task_id": 96,
			"application_id": 11,
			"task_id": 0,
			"data_in": 48,
			"data_out": 26,
			"can_offload": 1,
			"chosen_node_id": 4,
			"source_node_id": 2,
			"chosen_node_type": "edge",
			"input_upload_start_time": 0,
			"input_upload_finish_time": 0,
			"process_start_time": 3846.77,
			"process_finish_time": 3980.11,
			"output_upload_start_time": 0,
			"output_upload_finish_time": 0,
			"parents": [
			],
			"parent_upload_windows": {
			}
		},
		{
			"task_name": "APP_8_Inner_Layer_0:0",
			"total_task_id": 72,
			"application_id": 8,
			"task_id": 1,
			"data_in": 46,
			"data_out": 18,
			"can_offload": 1,
			"chosen_node_id": 1,
			"source_node_id": 2,
			"chosen_node_type": "edge",
			"input_upload_start_time": 0,
			"input_upload_finish_time": 0,
			"process_start_time": 3572.78,
			"process_finish_time": 4106.12,
			"output_upload_start_time": 0,
			"output_upload_finish_time": 0,
			"parents": [
				"APP_8_Input_Layer_0"
			],
			"parent_upload_windows": {
			}
		},
		{
			"task_name": "APP_11_Inner_Layer_0:0",
			"total_task_id": 97,
			"application_id": 11,
			"task_id": 1,
			"data_in": 26,
			"data_out": 32,
			"can_offload": 1,
			"chosen_node_id": 4,
			"source_node_id": 2,
			"chosen_node_type": "edge",
			"input_upload_start_time": 0,
			"input_upload_finish_time": 0,
			"process_start_time": 3981.11,
			"process_finish_time": 4114.44,
			"output_upload_start_time": 0,
			"output_upload_finish_time": 0,
			"parents": [
				"APP_11_Input_Layer_0"
			],
			"parent_upload_windows": {
			}
		},
		{
			"task_name": "APP_7_Inner_Layer_2:1",
			"total_task_id": 69,
			"application_id": 7,
			"task_id": 6,
			"data_in": 32,
			"data_out": 34,
			"can_offload": 1,
			"chosen_node_id": 3,
			"source_node_id": 2,
			"chosen_node_type": "edge",
			"input_upload_start_time": 0,
			"input_upload_finish_time": 0,
			"process_start_time": 3621.83,
			"process_finish_time": 4155.16,
			"output_upload_start_time": 0,
			"output_upload_finish_time": 0,
			"parents": [
				"APP_7_Inner_Layer_1:0"
			],
			"parent_upload_windows": {
			}
		},
		{
			"task_name": "APP_8_Inner_Layer_1:1",
			"total_task_id": 74,
			"application_id": 8,
			"task_id": 3,
			"data_in": 12,
			"data_out": 27,
			"can_offload": 1,
			"chosen_node_id": 1,
			"source_node_id": 2,
			"chosen_node_type": "edge",
			"input_upload_start_time": 0,
			"input_upload_finish_time": 0,
			"process_start_time": 4107.12,
			"process_finish_time": 4173.78,
			"output_upload_start_time": 0,
			"output_upload_finish_time": 0,
			"parents": [
				"APP_8_Inner_Layer_0:0"
			],
			"parent_upload_windows": {
			}
		},
		{
			"task_name": "APP_9_Inner_Layer_0:0",
			"total_task_id": 85,
			"application_id": 9,
			"task_id": 1,
			"data_in": 19,
			"data_out": 46,
			"can_offload": 1,
			"chosen_node_id": 3,
			"source_node_id": 2,
			"chosen_node_type": "edge",
			"input_upload_start_time": 0,
			"input_upload_finish_time": 0,
			"process_start_time": 3617.97,
			"process_finish_time": 4217.97,
			"output_upload_start_time": 0,
			"output_upload_finish_time": 0,
			"parents": [
				"APP_9_Input_Layer_0"
			],
			"parent_upload_windows": {
			}
		},
		{
			"task_name": "APP_9_Inner_Layer_1:0",
			"total_task_id": 86,
			"application_id": 9,
			"task_id": 2,
			"data_in": 35,
			"data_out": 3,
			"can_offload": 1,
			"chosen_node_id": 3,
			"source_node_id": 2,
			"chosen_node_type": "edge",
			"input_upload_start_time": 0,
			"input_upload_finish_time": 0,
			"process_start_time": 4218.97,
			"process_finish_time": 4285.63,
			"output_upload_start_time": 0,
			"output_upload_finish_time": 0,
			"parents": [
				"APP_9_Inner_Layer_0:0"
			],
			"parent_upload_windows": {
			}
		},
		{
			"task_name": "APP_9_Inner_Layer_1:1",
			"total_task_id": 87,
			"application_id": 9,
			"task_id": 3,
			"data_in": 45,
			"data_out": 35,
			"can_offload": 1,
			"chosen_node_id": 3,
			"source_node_id": 2,
			"chosen_node_type": "edge",
			"input_upload_start_time": 0,
			"input_upload_finish_time": 0,
			"process_start_time": 4218.97,
			"process_finish_time": 4285.63,
			"output_upload_start_time": 0,
			"output_upload_finish_time": 0,
			"parents": [
				"APP_9_Inner_Layer_0:0"
			],
			"parent_upload_windows": {
			}
		},
		{
			"task_name": "APP_6_Inner_Layer_2:0",
			"total_task_id": 58,
			"application_id": 6,
			"task_id": 4,
			"data_in": 23,
			"data_out": 6,
			"can_offload": 1,
			"chosen_node_id": 4,
			"source_node_id": 2,
			"chosen_node_type": "edge",
			"input_upload_start_time": 0,
			"input_upload_finish_time": 0,
			"process_start_time": 3845.77,
			"process_finish_time": 4312.44,
			"output_upload_start_time": 0,
			"output_upload_finish_time": 0,
			"parents": [
				"APP_6_Inner_Layer_1:0"
			],
			"parent_upload_windows": {
			}
		},
		{
			"task_name": "APP_10_Input_Layer_0",
			"total_task_id": 91,
			"application_id": 10,
			"task_id": 0,
			"data_in": 5,
			"data_out": 26,
			"can_offload": 1,
			"chosen_node_id": 0,
			"source_node_id": 2,
			"chosen_node_type": "cloud",
			"input_upload_start_time": 0,
			"input_upload_finish_time": 0,
			"process_start_time": 3728.51,
			"process_finish_time": 4328.51,
			"output_upload_start_time": 0,
			"output_upload_finish_time": 0,
			"parents": [
			],
			"parent_upload_windows": {
			}
		},
		{
			"task_name": "APP_9_Inner_Layer_1:2",
			"total_task_id": 88,
			"application_id": 9,
			"task_id": 4,
			"data_in": 38,
			"data_out": 33,
			"can_offload": 1,
			"chosen_node_id": 1,
			"source_node_id": 2,
			"chosen_node_type": "edge",
			"input_upload_start_time": 4218.97,
			"input_upload_finish_time": 4273.89,
			"process_start_time": 4273.89,
			"process_finish_time": 4340.55,
			"output_upload_start_time": 0,
			"output_upload_finish_time": 0,
			"parents": [
				"APP_9_Inner_Layer_0:0"
			],
			"parent_upload_windows": {
				"3": [
					["4218.97", "4273.89"]
				]
			}
		},
		{
			"task_name": "APP_6_Inner_Layer_3:1",
			"total_task_id": 60,
			"application_id": 6,
			"task_id": 6,
			"data_in": 8,
			"data_out": 22,
			"can_offload": 1,
			"chosen_node_id": 3,
			"source_node_id": 2,
			"chosen_node_type": "edge",
			"input_upload_start_time": 4313.44,
			"input_upload_finish_time": 4329.3,
			"process_start_time": 4329.3,
			"process_finish_time": 4395.97,
			"output_upload_start_time": 0,
			"output_upload_finish_time": 0,
			"parents": [
				"APP_6_Inner_Layer_2:0"
			],
			"parent_upload_windows": {
				"4": [
					["4313.44", "4329.3"]
				]
			}
		},
		{
			"task_name": "APP_8_Inner_Layer_1:0",
			"total_task_id": 73,
			"application_id": 8,
			"task_id": 2,
			"data_in": 23,
			"data_out": 11,
			"can_offload": 1,
			"chosen_node_id": 1,
			"source_node_id": 2,
			"chosen_node_type": "edge",
			"input_upload_start_time": 0,
			"input_upload_finish_time": 0,
			"process_start_time": 4107.12,
			"process_finish_time": 4440.45,
			"output_upload_start_time": 0,
			"output_upload_finish_time": 0,
			"parents": [
				"APP_8_Inner_Layer_0:0"
			],
			"parent_upload_windows": {
			}
		},
		{
			"task_name": "APP_7_Output_Layer_0",
			"total_task_id": 70,
			"application_id": 7,
			"task_id": 7,
			"data_in": 36,
			"data_out": 31,
			"can_offload": 1,
			"chosen_node_id": 0,
			"source_node_id": 2,
			"chosen_node_type": "cloud",
			"input_upload_start_time": 4156.16,
			"input_upload_finish_time": 4212.29,
			"process_start_time": 4212.29,
			"process_finish_time": 4478.96,
			"output_upload_start_time": 0,
			"output_upload_finish_time": 0,
			"parents": [
				"APP_7_Inner_Layer_2:0",
				"APP_7_Inner_Layer_2:1"
			],
			"parent_upload_windows": {
				"3": [
					["4156.16", "4209.36"]
				],
				"1": [
					["4156.16", "4212.29"]
				]
			}
		},
		{
			"task_name": "APP_10_Inner_Layer_0:0",
			"total_task_id": 92,
			"application_id": 10,
			"task_id": 1,
			"data_in": 12,
			"data_out": 44,
			"can_offload": 1,
			"chosen_node_id": 0,
			"source_node_id": 2,
			"chosen_node_type": "cloud",
			"input_upload_start_time": 0,
			"input_upload_finish_time": 0,
			"process_start_time": 4329.51,
			"process_finish_time": 4529.51,
			"output_upload_start_time": 0,
			"output_upload_finish_time": 0,
			"parents": [
				"APP_10_Input_Layer_0"
			],
			"parent_upload_windows": {
			}
		},
		{
			"task_name": "APP_8_Inner_Layer_1:2",
			"total_task_id": 75,
			"application_id": 8,
			"task_id": 4,
			"data_in": 5,
			"data_out": 35,
			"can_offload": 1,
			"chosen_node_id": 4,
			"source_node_id": 2,
			"chosen_node_type": "edge",
			"input_upload_start_time": 4107.12,
			"input_upload_finish_time": 4134.7,
			"process_start_time": 4134.7,
			"process_finish_time": 4534.7,
			"output_upload_start_time": 0,
			"output_upload_finish_time": 0,
			"parents": [
				"APP_8_Inner_Layer_0:0"
			],
			"parent_upload_windows": {
				"1": [
					["4107.12", "4134.7"]
				]
			}
		},
		{
			"task_name": "APP_12_Input_Layer_0",
			"total_task_id": 99,
			"application_id": 12,
			"task_id": 0,
			"data_in": 20,
			"data_out": 21,
			"can_offload": 1,
			"chosen_node_id": 1,
			"source_node_id": 2,
			"chosen_node_type": "edge",
			"input_upload_start_time": 0,
			"input_upload_finish_time": 0,
			"process_start_time": 4341.55,
			"process_finish_time": 4541.55,
			"output_upload_start_time": 0,
			"output_upload_finish_time": 0,
			"parents": [
			],
			"parent_upload_windows": {
			}
		},
		{
			"task_name": "APP_12_Inner_Layer_0:0",
			"total_task_id": 100,
			"application_id": 12,
			"task_id": 1,
			"data_in": 40,
			"data_out": 7,
			"can_offload": 1,
			"chosen_node_id": 1,
			"source_node_id": 2,
			"chosen_node_type": "edge",
			"input_upload_start_time": 0,
			"input_upload_finish_time": 0,
			"process_start_time": 4542.55,
			"process_finish_time": 4609.22,
			"output_upload_start_time": 0,
			"output_upload_finish_time": 0,
			"parents": [
				"APP_12_Input_Layer_0"
			],
			"parent_upload_windows": {
			}
		},
		{
			"task_name": "APP_10_Inner_Layer_0:1",
			"total_task_id": 93,
			"application_id": 10,
			"task_id": 2,
			"data_in": 7,
			"data_out": 37,
			"can_offload": 1,
			"chosen_node_id": 0,
			"source_node_id": 2,
			"chosen_node_type": "cloud",
			"input_upload_start_time": 0,
			"input_upload_finish_time": 0,
			"process_start_time": 4329.51,
			"process_finish_time": 4662.84,
			"output_upload_start_time": 0,
			"output_upload_finish_time": 0,
			"parents": [
				"APP_10_Input_Layer_0"
			],
			"parent_upload_windows": {
			}
		},
		{
			"task_name": "APP_11_Output_Layer_0",
			"total_task_id": 98,
			"application_id": 11,
			"task_id": 2,
			"data_in": 4,
			"data_out": 38,
			"can_offload": 1,
			"chosen_node_id": 0,
			"source_node_id": 2,
			"chosen_node_type": "cloud",
			"input_upload_start_time": 4115.44,
			"input_upload_finish_time": 4166.69,
			"process_start_time": 4166.69,
			"process_finish_time": 4700.02,
			"output_upload_start_time": 0,
			"output_upload_finish_time": 0,
			"parents": [
				"APP_11_Inner_Layer_0:0"
			],
			"parent_upload_windows": {
				"4": [
					["4115.44", "4166.69"]
				]
			}
		},
		{
			"task_name": "APP_6_Inner_Layer_3:0",
			"total_task_id": 59,
			"application_id": 6,
			"task_id": 5,
			"data_in": 43,
			"data_out": 4,
			"can_offload": 1,
			"chosen_node_id": 4,
			"source_node_id": 2,
			"chosen_node_type": "edge",
			"input_upload_start_time": 0,
			"input_upload_finish_time": 0,
			"process_start_time": 4313.44,
			"process_finish_time": 4713.44,
			"output_upload_start_time": 0,
			"output_upload_finish_time": 0,
			"parents": [
				"APP_6_Inner_Layer_2:0"
			],
			"parent_upload_windows": {
			}
		},
		{
			"task_name": "APP_13_Input_Layer_0",
			"total_task_id": 106,
			"application_id": 13,
			"task_id": 0,
			"data_in": 37,
			"data_out": 31,
			"can_offload": 1,
			"chosen_node_id": 0,
			"source_node_id": 2,
			"chosen_node_type": "cloud",
			"input_upload_start_time": 0,
			"input_upload_finish_time": 0,
			"process_start_time": 4543.55,
			"process_finish_time": 4743.55,
			"output_upload_start_time": 0,
			"output_upload_finish_time": 0,
			"parents": [
			],
			"parent_upload_windows": {
			}
		},
		{
			"task_name": "APP_10_Inner_Layer_0:2",
			"total_task_id": 94,
			"application_id": 10,
			"task_id": 3,
			"data_in": 39,
			"data_out": 21,
			"can_offload": 1,
			"chosen_node_id": 0,
			"source_node_id": 2,
			"chosen_node_type": "cloud",
			"input_upload_start_time": 0,
			"input_upload_finish_time": 0,
			"process_start_time": 4329.51,
			"process_finish_time": 4796.18,
			"output_upload_start_time": 0,
			"output_upload_finish_time": 0,
			"parents": [
				"APP_10_Input_Layer_0"
			],
			"parent_upload_windows": {
			}
		},
		{
			"task_name": "APP_13_Inner_Layer_0:3",
			"total_task_id": 110,
			"application_id": 13,
			"task_id": 4,
			"data_in": 43,
			"data_out": 11,
			"can_offload": 1,
			"chosen_node_id": 0,
			"source_node_id": 2,
			"chosen_node_type": "cloud",
			"input_upload_start_time": 0,
			"input_upload_finish_time": 0,
			"process_start_time": 4744.55,
			"process_finish_time": 4877.89,
			"output_upload_start_time": 0,
			"output_upload_finish_time": 0,
			"parents": [
				"APP_13_Input_Layer_0"
			],
			"parent_upload_windows": {
			}
		},
		{
			"task_name": "APP_8_Inner_Layer_2:1",
			"total_task_id": 77,
			"application_id": 8,
			"task_id": 6,
			"data_in": 21,
			"data_out": 12,
			"can_offload": 1,
			"chosen_node_id": 3,
			"source_node_id": 2,
			"chosen_node_type": "edge",
			"input_upload_start_time": 4535.7,
			"input_upload_finish_time": 4579.88,
			"process_start_time": 4579.88,
			"process_finish_time": 4913.21,
			"output_upload_start_time": 0,
			"output_upload_finish_time": 0,
			"parents": [
				"APP_8_Inner_Layer_1:0",
				"APP_8_Inner_Layer_1:2"
			],
			"parent_upload_windows": {
				"1": [
					["4535.7", "4556.44"]
				],
				"4": [
					["4535.7", "4579.88"]
				]
			}
		},
		{
			"task_name": "APP_6_Inner_Layer_3:2",
			"total_task_id": 61,
			"application_id": 6,
			"task_id": 7,
			"data_in": 30,
			"data_out": 10,
			"can_offload": 1,
			"chosen_node_id": 0,
			"source_node_id": 2,
			"chosen_node_type": "cloud",
			"input_upload_start_time": 4313.44,
			"input_upload_finish_time": 4339.3,
			"process_start_time": 4339.3,
			"process_finish_time": 4939.3,
			"output_upload_start_time": 0,
			"output_upload_finish_time": 0,
			"parents": [
				"APP_6_Inner_Layer_2:0"
			],
			"parent_upload_windows": {
				"4": [
					["4313.44", "4339.3"]
				]
			}
		},
		{
			"task_name": "APP_8_Inner_Layer_2:0",
			"total_task_id": 76,
			"application_id": 8,
			"task_id": 5,
			"data_in": 30,
			"data_out": 33,
			"can_offload": 1,
			"chosen_node_id": 1,
			"source_node_id": 2,
			"chosen_node_type": "edge",
			"input_upload_start_time": 4535.7,
			"input_upload_finish_time": 4579.88,
			"process_start_time": 4579.88,
			"process_finish_time": 4979.88,
			"output_upload_start_time": 0,
			"output_upload_finish_time": 0,
			"parents": [
				"APP_8_Inner_Layer_1:1",
				"APP_8_Inner_Layer_1:0",
				"APP_8_Inner_Layer_1:2"
			],
			"parent_upload_windows": {
				"4": [
					["4535.7", "4579.88"]
				]
			}
		},
		{
			"task_name": "APP_9_Inner_Layer_2:0",
			"total_task_id": 89,
			"application_id": 9,
			"task_id": 5,
			"data_in": 37,
			"data_out": 33,
			"can_offload": 1,
			"chosen_node_id": 3,
			"source_node_id": 2,
			"chosen_node_type": "edge",
			"input_upload_start_time": 4341.55,
			"input_upload_finish_time": 4383.78,
			"process_start_time": 4383.78,
			"process_finish_time": 4983.78,
			"output_upload_start_time": 0,
			"output_upload_finish_time": 0,
			"parents": [
				"APP_9_Inner_Layer_1:1",
				"APP_9_Inner_Layer_1:0",
				"APP_9_Inner_Layer_1:2"
			],
			"parent_upload_windows": {
				"1": [
					["4341.55", "4383.78"]
				]
			}
		},
		{
			"task_name": "APP_12_Inner_Layer_0:1",
			"total_task_id": 101,
			"application_id": 12,
			"task_id": 2,
			"data_in": 46,
			"data_out": 7,
			"can_offload": 1,
			"chosen_node_id": 0,
			"source_node_id": 2,
			"chosen_node_type": "cloud",
			"input_upload_start_time": 4566.44,
			"input_upload_finish_time": 4606.95,
			"process_start_time": 4606.95,
			"process_finish_time": 5006.95,
			"output_upload_start_time": 0,
			"output_upload_finish_time": 0,
			"parents": [
				"APP_12_Input_Layer_0"
			],
			"parent_upload_windows": {
				"1": [
					["4566.44", "4606.95"]
				]
			}
		},
		{
			"task_name": "APP_13_Inner_Layer_0:0",
			"total_task_id": 107,
			"application_id": 13,
			"task_id": 1,
			"data_in": 30,
			"data_out": 24,
			"can_offload": 1,
			"chosen_node_id": 0,
			"source_node_id": 2,
			"chosen_node_type": "cloud",
			"input_upload_start_time": 0,
			"input_upload_finish_time": 0,
			"process_start_time": 4744.55,
			"process_finish_time": 5077.89,
			"output_upload_start_time": 0,
			"output_upload_finish_time": 0,
			"parents": [
				"APP_13_Input_Layer_0"
			],
			"parent_upload_windows": {
			}
		},
		{
			"task_name": "APP_13_Inner_Layer_0:2",
			"total_task_id": 109,
			"application_id": 13,
			"task_id": 3,
			"data_in": 3,
			"data_out": 22,
			"can_offload": 1,
			"chosen_node_id": 0,
			"source_node_id": 2,
			"chosen_node_type": "cloud",
			"input_upload_start_time": 0,
			"input_upload_finish_time": 0,
			"process_start_time": 4744.55,
			"process_finish_time": 5077.89,
			"output_upload_start_time": 0,
			"output_upload_finish_time": 0,
			"parents": [
				"APP_13_Input_Layer_0"
			],
			"parent_upload_windows": {
			}
		},
		{
			"task_name": "APP_12_Inner_Layer_0:3",
			"total_task_id": 103,
			"application_id": 12,
			"task_id": 4,
			"data_in": 30,
			"data_out": 34,
			"can_offload": 1,
			"chosen_node_id": 0,
			"source_node_id": 2,
			"chosen_node_type": "cloud",
			"input_upload_start_time": 4647.45,
			"input_upload_finish_time": 4687.96,
			"process_start_time": 4687.96,
			"process_finish_time": 5087.96,
			"output_upload_start_time": 0,
			"output_upload_finish_time": 0,
			"parents": [
				"APP_12_Input_Layer_0"
			],
			"parent_upload_windows": {
				"1": [
					["4647.45", "4687.96"]
				]
			}
		},
		{
			"task_name": "APP_8_Inner_Layer_2:2",
			"total_task_id": 78,
			"application_id": 8,
			"task_id": 7,
			"data_in": 24,
			"data_out": 37,
			"can_offload": 1,
			"chosen_node_id": 0,
			"source_node_id": 2,
			"chosen_node_type": "cloud",
			"input_upload_start_time": 4535.7,
			"input_upload_finish_time": 4589.88,
			"process_start_time": 4589.88,
			"process_finish_time": 5123.21,
			"output_upload_start_time": 0,
			"output_upload_finish_time": 0,
			"parents": [
				"APP_8_Inner_Layer_1:0",
				"APP_8_Inner_Layer_1:2"
			],
			"parent_upload_windows": {
				"1": [
					["4535.7", "4566.44"]
				],
				"4": [
					["4535.7", "4589.88"]
				]
			}
		},
		{
			"task_name": "APP_8_Inner_Layer_2:3",
			"total_task_id": 79,
			"application_id": 8,
			"task_id": 8,
			"data_in": 35,
			"data_out": 31,
			"can_offload": 1,
			"chosen_node_id": 4,
			"source_node_id": 2,
			"chosen_node_type": "edge",
			"input_upload_start_time": 0,
			"input_upload_finish_time": 0,
			"process_start_time": 4535.7,
			"process_finish_time": 5135.7,
			"output_upload_start_time": 0,
			"output_upload_finish_time": 0,
			"parents": [
				"APP_8_Inner_Layer_1:2"
			],
			"parent_upload_windows": {
			}
		},
		{
			"task_name": "APP_13_Inner_Layer_0:1",
			"total_task_id": 108,
			"application_id": 13,
			"task_id": 2,
			"data_in": 25,
			"data_out": 17,
			"can_offload": 1,
			"chosen_node_id": 0,
			"source_node_id": 2,
			"chosen_node_type": "cloud",
			"input_upload_start_time": 0,
			"input_upload_finish_time": 0,
			"process_start_time": 4744.55,
			"process_finish_time": 5144.55,
			"output_upload_start_time": 0,
			"output_upload_finish_time": 0,
			"parents": [
				"APP_13_Input_Layer_0"
			],
			"parent_upload_windows": {
			}
		},
		{
			"task_name": "APP_6_Output_Layer_0",
			"total_task_id": 62,
			"application_id": 6,
			"task_id": 8,
			"data_in": 30,
			"data_out": 49,
			"can_offload": 1,
			"chosen_node_id": 3,
			"source_node_id": 2,
			"chosen_node_type": "edge",
			"input_upload_start_time": 4940.3,
			"input_upload_finish_time": 4970.06,
			"process_start_time": 4970.06,
			"process_finish_time": 5170.06,
			"output_upload_start_time": 0,
			"output_upload_finish_time": 0,
			"parents": [
				"APP_6_Inner_Layer_3:0",
				"APP_6_Inner_Layer_3:1",
				"APP_6_Inner_Layer_3:2"
			],
			"parent_upload_windows": {
				"0": [
					["4940.3", "4970.06"]
				],
				"4": [
					["4940.3", "4954.21"]
				]
			}
		},
		{
			"task_name": "APP_13_Inner_Layer_1:1",
			"total_task_id": 112,
			"application_id": 13,
			"task_id": 6,
			"data_in": 38,
			"data_out": 5,
			"can_offload": 1,
			"chosen_node_id": 0,
			"source_node_id": 2,
			"chosen_node_type": "cloud",
			"input_upload_start_time": 0,
			"input_upload_finish_time": 0,
			"process_start_time": 5145.55,
			"process_finish_time": 5212.22,
			"output_upload_start_time": 0,
			"output_upload_finish_time": 0,
			"parents": [
				"APP_13_Inner_Layer_0:1"
			],
			"parent_upload_windows": {
			}
		},
		{
			"task_name": "APP_13_Inner_Layer_1:3",
			"total_task_id": 114,
			"application_id": 13,
			"task_id": 8,
			"data_in": 38,
			"data_out": 47,
			"can_offload": 1,
			"chosen_node_id": 0,
			"source_node_id": 2,
			"chosen_node_type": "cloud",
			"input_upload_start_time": 0,
			"input_upload_finish_time": 0,
			"process_start_time": 5145.55,
			"process_finish_time": 5212.22,
			"output_upload_start_time": 0,
			"output_upload_finish_time": 0,
			"parents": [
				"APP_13_Inner_Layer_0:1"
			],
			"parent_upload_windows": {
			}
		},
		{
			"task_name": "APP_12_Inner_Layer_0:2",
			"total_task_id": 102,
			"application_id": 12,
			"task_id": 3,
			"data_in": 16,
			"data_out": 17,
			"can_offload": 1,
			"chosen_node_id": 0,
			"source_node_id": 2,
			"chosen_node_type": "cloud",
			"input_upload_start_time": 4606.95,
			"input_upload_finish_time": 4647.45,
			"process_start_time": 4647.45,
			"process_finish_time": 5247.45,
			"output_upload_start_time": 0,
			"output_upload_finish_time": 0,
			"parents": [
				"APP_12_Input_Layer_0"
			],
			"parent_upload_windows": {
				"1": [
					["4606.95", "4647.45"]
				]
			}
		},
		{
			"task_name": "APP_8_Inner_Layer_3:2",
			"total_task_id": 82,
			"application_id": 8,
			"task_id": 11,
			"data_in": 16,
			"data_out": 2,
			"can_offload": 1,
			"chosen_node_id": 4,
			"source_node_id": 2,
			"chosen_node_type": "edge",
			"input_upload_start_time": 0,
			"input_upload_finish_time": 0,
			"process_start_time": 5136.7,
			"process_finish_time": 5336.7,
			"output_upload_start_time": 0,
			"output_upload_finish_time": 0,
			"parents": [
				"APP_8_Inner_Layer_2:3"
			],
			"parent_upload_windows": {
			}
		},
		{
			"task_name": "APP_14_Input_Layer_0",
			"total_task_id": 116,
			"application_id": 14,
			"task_id": 0,
			"data_in": 48,
			"data_out": 21,
			"can_offload": 1,
			"chosen_node_id": 3,
			"source_node_id": 2,
			"chosen_node_type": "edge",
			"input_upload_start_time": 0,
			"input_upload_finish_time": 0,
			"process_start_time": 5007.95,
			"process_finish_time": 5341.28,
			"output_upload_start_time": 0,
			"output_upload_finish_time": 0,
			"parents": [
			],
			"parent_upload_windows": {
			}
		},
		{
			"task_name": "APP_10_Output_Layer_0",
			"total_task_id": 95,
			"application_id": 10,
			"task_id": 4,
			"data_in": 14,
			"data_out": 28,
			"can_offload": 1,
			"chosen_node_id": 0,
			"source_node_id": 2,
			"chosen_node_type": "cloud",
			"input_upload_start_time": 0,
			"input_upload_finish_time": 0,
			"process_start_time": 4796.18,
			"process_finish_time": 5396.18,
			"output_upload_start_time": 0,
			"output_upload_finish_time": 0,
			"parents": [
				"APP_10_Inner_Layer_0:2",
				"APP_10_Inner_Layer_0:1",
				"APP_10_Inner_Layer_0:0"
			],
			"parent_upload_windows": {
			}
		},
		{
			"task_name": "APP_14_Inner_Layer_0:1",
			"total_task_id": 118,
			"application_id": 14,
			"task_id": 2,
			"data_in": 39,
			"data_out": 26,
			"can_offload": 1,
			"chosen_node_id": 3,
			"source_node_id": 2,
			"chosen_node_type": "edge",
			"input_upload_start_time": 0,
			"input_upload_finish_time": 0,
			"process_start_time": 5342.28,
			"process_finish_time": 5408.95,
			"output_upload_start_time": 0,
			"output_upload_finish_time": 0,
			"parents": [
				"APP_14_Input_Layer_0"
			],
			"parent_upload_windows": {
			}
		},
		{
			"task_name": "APP_13_Inner_Layer_1:0",
			"total_task_id": 111,
			"application_id": 13,
			"task_id": 5,
			"data_in": 3,
			"data_out": 23,
			"can_offload": 1,
			"chosen_node_id": 0,
			"source_node_id": 2,
			"chosen_node_type": "cloud",
			"input_upload_start_time": 0,
			"input_upload_finish_time": 0,
			"process_start_time": 5145.55,
			"process_finish_time": 5412.22,
			"output_upload_start_time": 0,
			"output_upload_finish_time": 0,
			"parents": [
				"APP_13_Inner_Layer_0:3",
				"APP_13_Inner_Layer_0:2",
				"APP_13_Inner_Layer_0:1"
			],
			"parent_upload_windows": {
			}
		},
		{
			"task_name": "APP_12_Inner_Layer_1:0",
			"total_task_id": 104,
			"application_id": 12,
			"task_id": 5,
			"data_in": 22,
			"data_out": 12,
			"can_offload": 1,
			"chosen_node_id": 0,
			"source_node_id": 2,
			"chosen_node_type": "cloud",
			"input_upload_start_time": 5088.96,
			"input_upload_finish_time": 5115.8,
			"process_start_time": 5247.45,
			"process_finish_time": 5447.45,
			"output_upload_start_time": 0,
			"output_upload_finish_time": 0,
			"parents": [
				"APP_12_Inner_Layer_0:0",
				"APP_12_Inner_Layer_0:1",
				"APP_12_Inner_Layer_0:2",
				"APP_12_Inner_Layer_0:3"
			],
			"parent_upload_windows": {
				"1": [
					["5088.96", "5115.8"]
				]
			}
		},
		{
			"task_name": "APP_13_Inner_Layer_1:2",
			"total_task_id": 113,
			"application_id": 13,
			"task_id": 7,
			"data_in": 22,
			"data_out": 48,
			"can_offload": 1,
			"chosen_node_id": 0,
			"source_node_id": 2,
			"chosen_node_type": "cloud",
			"input_upload_start_time": 0,
			"input_upload_finish_time": 0,
			"process_start_time": 5078.89,
			"process_finish_time": 5612.22,
			"output_upload_start_time": 0,
			"output_upload_finish_time": 0,
			"parents": [
				"APP_13_Inner_Layer_0:0"
			],
			"parent_upload_windows": {
			}
		},
		{
			"task_name": "APP_14_Inner_Layer_0:0",
			"total_task_id": 117,
			"application_id": 14,
			"task_id": 1,
			"data_in": 18,
			"data_out": 39,
			"can_offload": 1,
			"chosen_node_id": 3,
			"source_node_id": 2,
			"chosen_node_type": "edge",
			"input_upload_start_time": 0,
			"input_upload_finish_time": 0,
			"process_start_time": 5342.28,
			"process_finish_time": 5675.61,
			"output_upload_start_time": 0,
			"output_upload_finish_time": 0,
			"parents": [
				"APP_14_Input_Layer_0"
			],
			"parent_upload_windows": {
			}
		},
		{
			"task_name": "APP_14_Inner_Layer_1:0",
			"total_task_id": 119,
			"application_id": 14,
			"task_id": 3,
			"data_in": 30,
			"data_out": 47,
			"can_offload": 1,
			"chosen_node_id": 3,
			"source_node_id": 2,
			"chosen_node_type": "edge",
			"input_upload_start_time": 0,
			"input_upload_finish_time": 0,
			"process_start_time": 5409.95,
			"process_finish_time": 5676.61,
			"output_upload_start_time": 0,
			"output_upload_finish_time": 0,
			"parents": [
				"APP_14_Inner_Layer_0:1"
			],
			"parent_upload_windows": {
			}
		},
		{
			"task_name": "APP_8_Inner_Layer_3:0",
			"total_task_id": 80,
			"application_id": 8,
			"task_id": 9,
			"data_in": 9,
			"data_out": 10,
			"can_offload": 1,
			"chosen_node_id": 0,
			"source_node_id": 2,
			"chosen_node_type": "cloud",
			"input_upload_start_time": 5124.21,
			"input_upload_finish_time": 5155.93,
			"process_start_time": 5155.93,
			"process_finish_time": 5689.26,
			"output_upload_start_time": 0,
			"output_upload_finish_time": 0,
			"parents": [
				"APP_8_Inner_Layer_2:1",
				"APP_8_Inner_Layer_2:2"
			],
			"parent_upload_windows": {
				"3": [
					["5124.21", "5155.93"]
				]
			}
		},
		{
			"task_name": "APP_8_Inner_Layer_3:1",
			"total_task_id": 81,
			"application_id": 8,
			"task_id": 10,
			"data_in": 15,
			"data_out": 46,
			"can_offload": 1,
			"chosen_node_id": 4,
			"source_node_id": 2,
			"chosen_node_type": "edge",
			"input_upload_start_time": 5124.21,
			"input_upload_finish_time": 5180.34,
			"process_start_time": 5180.34,
			"process_finish_time": 5713.67,
			"output_upload_start_time": 0,
			"output_upload_finish_time": 0,
			"parents": [
				"APP_8_Inner_Layer_2:1",
				"APP_8_Inner_Layer_2:0",
				"APP_8_Inner_Layer_2:2"
			],
			"parent_upload_windows": {
				"3": [
					["5124.21", "5145.93"]
				],
				"1": [
					["5124.21", "5166.44"]
				],
				"0": [
					["5124.21", "5180.34"]
				]
			}
		},
		{
			"task_name": "APP_14_Inner_Layer_1:1",
			"total_task_id": 120,
			"application_id": 14,
			"task_id": 4,
			"data_in": 23,
			"data_out": 10,
			"can_offload": 1,
			"chosen_node_id": 3,
			"source_node_id": 2,
			"chosen_node_type": "edge",
			"input_upload_start_time": 0,
			"input_upload_finish_time": 0,
			"process_start_time": 5676.61,
			"process_finish_time": 5876.61,
			"output_upload_start_time": 0,
			"output_upload_finish_time": 0,
			"parents": [
				"APP_14_Inner_Layer_0:1",
				"APP_14_Inner_Layer_0:0"
			],
			"parent_upload_windows": {
			}
		},
		{
			"task_name": "APP_8_Output_Layer_0",
			"total_task_id": 83,
			"application_id": 8,
			"task_id": 12,
			"data_in": 22,
			"data_out": 15,
			"can_offload": 1,
			"chosen_node_id": 4,
			"source_node_id": 2,
			"chosen_node_type": "edge",
			"input_upload_start_time": 5714.67,
			"input_upload_finish_time": 5744.44,
			"process_start_time": 5744.44,
			"process_finish_time": 5944.44,
			"output_upload_start_time": 0,
			"output_upload_finish_time": 0,
			"parents": [
				"APP_8_Inner_Layer_3:2",
				"APP_8_Inner_Layer_3:0",
				"APP_8_Inner_Layer_3:1"
			],
			"parent_upload_windows": {
				"0": [
					["5714.67", "5744.44"]
				]
			}
		},
		{
			"task_name": "APP_12_Output_Layer_0",
			"total_task_id": 105,
			"application_id": 12,
			"task_id": 6,
			"data_in": 1,
			"data_out": 44,
			"can_offload": 1,
			"chosen_node_id": 0,
			"source_node_id": 2,
			"chosen_node_type": "cloud",
			"input_upload_start_time": 0,
			"input_upload_finish_time": 0,
			"process_start_time": 5448.45,
			"process_finish_time": 6048.45,
			"output_upload_start_time": 0,
			"output_upload_finish_time": 0,
			"parents": [
				"APP_12_Inner_Layer_1:0"
			],
			"parent_upload_windows": {
			}
		},
		{
			"task_name": "APP_14_Inner_Layer_2:0",
			"total_task_id": 122,
			"application_id": 14,
			"task_id": 6,
			"data_in": 12,
			"data_out": 31,
			"can_offload": 1,
			"chosen_node_id": 3,
			"source_node_id": 2,
			"chosen_node_type": "edge",
			"input_upload_start_time": 0,
			"input_upload_finish_time": 0,
			"process_start_time": 5877.61,
			"process_finish_time": 6077.61,
			"output_upload_start_time": 0,
			"output_upload_finish_time": 0,
			"parents": [
				"APP_14_Inner_Layer_1:1"
			],
			"parent_upload_windows": {
			}
		},
		{
			"task_name": "APP_14_Inner_Layer_1:2",
			"total_task_id": 121,
			"application_id": 14,
			"task_id": 5,
			"data_in": 22,
			"data_out": 49,
			"can_offload": 1,
			"chosen_node_id": 3,
			"source_node_id": 2,
			"chosen_node_type": "edge",
			"input_upload_start_time": 0,
			"input_upload_finish_time": 0,
			"process_start_time": 5676.61,
			"process_finish_time": 6143.28,
			"output_upload_start_time": 0,
			"output_upload_finish_time": 0,
			"parents": [
				"APP_14_Inner_Layer_0:0"
			],
			"parent_upload_windows": {
			}
		},
		{
			"task_name": "APP_14_Inner_Layer_2:3",
			"total_task_id": 125,
			"application_id": 14,
			"task_id": 9,
			"data_in": 17,
			"data_out": 30,
			"can_offload": 1,
			"chosen_node_id": 3,
			"source_node_id": 2,
			"chosen_node_type": "edge",
			"input_upload_start_time": 0,
			"input_upload_finish_time": 0,
			"process_start_time": 6143.28,
			"process_finish_time": 6209.95,
			"output_upload_start_time": 0,
			"output_upload_finish_time": 0,
			"parents": [
				"APP_14_Inner_Layer_1:2",
				"APP_14_Inner_Layer_1:1"
			],
			"parent_upload_windows": {
			}
		},
		{
			"task_name": "APP_16_Input_Layer_0",
			"total_task_id": 136,
			"application_id": 16,
			"task_id": 0,
			"data_in": 27,
			"data_out": 16,
			"can_offload": 1,
			"chosen_node_id": 4,
			"source_node_id": 2,
			"chosen_node_type": "edge",
			"input_upload_start_time": 0,
			"input_upload_finish_time": 0,
			"process_start_time": 5878.61,
			"process_finish_time": 6278.61,
			"output_upload_start_time": 0,
			"output_upload_finish_time": 0,
			"parents": [
			],
			"parent_upload_windows": {
			}
		},
		{
			"task_name": "APP_14_Inner_Layer_2:2",
			"total_task_id": 124,
			"application_id": 14,
			"task_id": 8,
			"data_in": 16,
			"data_out": 18,
			"can_offload": 1,
			"chosen_node_id": 1,
			"source_node_id": 2,
			"chosen_node_type": "edge",
			"input_upload_start_time": 5877.61,
			"input_upload_finish_time": 5953.28,
			"process_start_time": 5953.28,
			"process_finish_time": 6286.61,
			"output_upload_start_time": 0,
			"output_upload_finish_time": 0,
			"parents": [
				"APP_14_Inner_Layer_1:0",
				"APP_14_Inner_Layer_1:1"
			],
			"parent_upload_windows": {
				"3": [
					["5877.61", "5933.51"],
					["5933.51", "5953.28"]
				]
			}
		},
		{
			"task_name": "APP_16_Inner_Layer_0:2",
			"total_task_id": 139,
			"application_id": 16,
			"task_id": 3,
			"data_in": 20,
			"data_out": 26,
			"can_offload": 1,
			"chosen_node_id": 1,
			"source_node_id": 2,
			"chosen_node_type": "edge",
			"input_upload_start_time": 6279.61,
			"input_upload_finish_time": 6305.24,
			"process_start_time": 6305.24,
			"process_finish_time": 6371.9,
			"output_upload_start_time": 0,
			"output_upload_finish_time": 0,
			"parents": [
				"APP_16_Input_Layer_0"
			],
			"parent_upload_windows": {
				"4": [
					["6279.61", "6305.24"]
				]
			}
		},
		{
			"task_name": "APP_14_Inner_Layer_2:1",
			"total_task_id": 123,
			"application_id": 14,
			"task_id": 7,
			"data_in": 16,
			"data_out": 29,
			"can_offload": 1,
			"chosen_node_id": 4,
			"source_node_id": 2,
			"chosen_node_type": "edge",
			"input_upload_start_time": 5877.61,
			"input_upload_finish_time": 5953.28,
			"process_start_time": 5953.28,
			"process_finish_time": 6553.28,
			"output_upload_start_time": 0,
			"output_upload_finish_time": 0,
			"parents": [
				"APP_14_Inner_Layer_1:0",
				"APP_14_Inner_Layer_1:1"
			],
			"parent_upload_windows": {
				"3": [
					["5877.61", "5933.51"],
					["5933.51", "5953.28"]
				]
			}
		},
		{
			"task_name": "APP_16_Inner_Layer_0:1",
			"total_task_id": 138,
			"application_id": 16,
			"task_id": 2,
			"data_in": 24,
			"data_out": 32,
			"can_offload": 1,
			"chosen_node_id": 3,
			"source_node_id": 2,
			"chosen_node_type": "edge",
			"input_upload_start_time": 6279.61,
			"input_upload_finish_time": 6305.24,
			"process_start_time": 6305.24,
			"process_finish_time": 6638.57,
			"output_upload_start_time": 0,
			"output_upload_finish_time": 0,
			"parents": [
				"APP_16_Input_Layer_0"
			],
			"parent_upload_windows": {
				"4": [
					["6279.61", "6305.24"]
				]
			}
		},
		{
			"task_name": "APP_16_Inner_Layer_0:0",
			"total_task_id": 137,
			"application_id": 16,
			"task_id": 1,
			"data_in": 36,
			"data_out": 19,
			"can_offload": 1,
			"chosen_node_id": 4,
			"source_node_id": 2,
			"chosen_node_type": "edge",
			"input_upload_start_time": 0,
			"input_upload_finish_time": 0,
			"process_start_time": 6279.61,
			"process_finish_time": 6812.95,
			"output_upload_start_time": 0,
			"output_upload_finish_time": 0,
			"parents": [
				"APP_16_Input_Layer_0"
			],
			"parent_upload_windows": {
			}
		},
		{
			"task_name": "APP_14_Output_Layer_0",
			"total_task_id": 126,
			"application_id": 14,
			"task_id": 10,
			"data_in": 18,
			"data_out": 29,
			"can_offload": 1,
			"chosen_node_id": 3,
			"source_node_id": 2,
			"chosen_node_type": "edge",
			"input_upload_start_time": 6286.61,
			"input_upload_finish_time": 6591.6,
			"process_start_time": 6591.6,
			"process_finish_time": 6858.26,
			"output_upload_start_time": 0,
			"output_upload_finish_time": 0,
			"parents": [
				"APP_14_Inner_Layer_2:0",
				"APP_14_Inner_Layer_2:2",
				"APP_14_Inner_Layer_2:1",
				"APP_14_Inner_Layer_2:3"
			],
			"parent_upload_windows": {
				"1": [
					["6286.61", "6314.19"]
				],
				"4": [
					["6553.28", "6591.6"]
				]
			}
		},
		{
			"task_name": "APP_16_Output_Layer_0",
			"total_task_id": 140,
			"application_id": 16,
			"task_id": 4,
			"data_in": 48,
			"data_out": 6,
			"can_offload": 1,
			"chosen_node_id": 4,
			"source_node_id": 2,
			"chosen_node_type": "edge",
			"input_upload_start_time": 6639.57,
			"input_upload_finish_time": 6680.82,
			"process_start_time": 6812.95,
			"process_finish_time": 7012.95,
			"output_upload_start_time": 0,
			"output_upload_finish_time": 0,
			"parents": [
				"APP_16_Inner_Layer_0:0",
				"APP_16_Inner_Layer_0:2",
				"APP_16_Inner_Layer_0:1"
			],
			"parent_upload_windows": {
				"3": [
					["6639.57", "6680.82"]
				],
				"1": [
					["6639.57", "6674.96"]
				]
			}
		},
		{
			"task_name": "APP_9_Output_Layer_0",
			"total_task_id": 90,
			"application_id": 9,
			"task_id": 6,
			"data_in": 23,
			"data_out": 6,
			"can_offload": 0,
			"chosen_node_id": 2,
			"source_node_id": 2,
			"chosen_node_type": "mobile",
			"input_upload_start_time": 4984.78,
			"input_upload_finish_time": 5214.78,
			"process_start_time": 5214.78,
			"process_finish_time": 7464.78,
			"output_upload_start_time": 0,
			"output_upload_finish_time": 0,
			"parents": [
				"APP_9_Inner_Layer_2:0"
			],
			"parent_upload_windows": {
				"3": [
					["4984.78", "5214.78"]
				]
			}
		},
		{
			"task_name": "APP_15_Input_Layer_0",
			"total_task_id": 127,
			"application_id": 15,
			"task_id": 0,
			"data_in": 19,
			"data_out": 42,
			"can_offload": 0,
			"chosen_node_id": 2,
			"source_node_id": 2,
			"chosen_node_type": "mobile",
			"input_upload_start_time": 0,
			"input_upload_finish_time": 0,
			"process_start_time": 7465.78,
			"process_finish_time": 7965.78,
			"output_upload_start_time": 0,
			"output_upload_finish_time": 0,
			"parents": [
			],
			"parent_upload_windows": {
			}
		},
		{
			"task_name": "APP_15_Inner_Layer_0:0",
			"total_task_id": 128,
			"application_id": 15,
			"task_id": 1,
			"data_in": 33,
			"data_out": 26,
			"can_offload": 1,
			"chosen_node_id": 2,
			"source_node_id": 2,
			"chosen_node_type": "mobile",
			"input_upload_start_time": 0,
			"input_upload_finish_time": 0,
			"process_start_time": 7966.78,
			"process_finish_time": 8216.78,
			"output_upload_start_time": 0,
			"output_upload_finish_time": 0,
			"parents": [
				"APP_15_Input_Layer_0"
			],
			"parent_upload_windows": {
			}
		},
		{
			"task_name": "APP_15_Inner_Layer_0:2",
			"total_task_id": 130,
			"application_id": 15,
			"task_id": 3,
			"data_in": 6,
			"data_out": 33,
			"can_offload": 1,
			"chosen_node_id": 3,
			"source_node_id": 2,
			"chosen_node_type": "edge",
			"input_upload_start_time": 7966.78,
			"input_upload_finish_time": 8256.78,
			"process_start_time": 8256.78,
			"process_finish_time": 8523.45,
			"output_upload_start_time": 0,
			"output_upload_finish_time": 0,
			"parents": [
				"APP_15_Input_Layer_0"
			],
			"parent_upload_windows": {
				"2": [
					["7966.78", "8256.78"]
				]
			}
		},
		{
			"task_name": "APP_15_Inner_Layer_0:1",
			"total_task_id": 129,
			"application_id": 15,
			"task_id": 2,
			"data_in": 35,
			"data_out": 18,
			"can_offload": 1,
			"chosen_node_id": 4,
			"source_node_id": 2,
			"chosen_node_type": "edge",
			"input_upload_start_time": 7966.78,
			"input_upload_finish_time": 8256.78,
			"process_start_time": 8256.78,
			"process_finish_time": 8523.45,
			"output_upload_start_time": 0,
			"output_upload_finish_time": 0,
			"parents": [
				"APP_15_Input_Layer_0"
			],
			"parent_upload_windows": {
				"2": [
					["7966.78", "8256.78"]
				]
			}
		},
		{
			"task_name": "APP_15_Inner_Layer_1:0",
			"total_task_id": 131,
			"application_id": 15,
			"task_id": 4,
			"data_in": 24,
			"data_out": 49,
			"can_offload": 1,
			"chosen_node_id": 1,
			"source_node_id": 2,
			"chosen_node_type": "edge",
			"input_upload_start_time": 8217.78,
			"input_upload_finish_time": 8401.11,
			"process_start_time": 8401.11,
			"process_finish_time": 8534.45,
			"output_upload_start_time": 0,
			"output_upload_finish_time": 0,
			"parents": [
				"APP_15_Inner_Layer_0:0"
			],
			"parent_upload_windows": {
				"2": [
					["8217.78", "8401.11"]
				]
			}
		},
		{
			"task_name": "APP_15_Inner_Layer_1:1",
			"total_task_id": 132,
			"application_id": 15,
			"task_id": 5,
			"data_in": 16,
			"data_out": 2,
			"can_offload": 1,
			"chosen_node_id": 3,
			"source_node_id": 2,
			"chosen_node_type": "edge",
			"input_upload_start_time": 0,
			"input_upload_finish_time": 0,
			"process_start_time": 8524.45,
			"process_finish_time": 8791.12,
			"output_upload_start_time": 0,
			"output_upload_finish_time": 0,
			"parents": [
				"APP_15_Inner_Layer_0:2"
			],
			"parent_upload_windows": {
			}
		},
		{
			"task_name": "APP_15_Inner_Layer_1:3",
			"total_task_id": 134,
			"application_id": 15,
			"task_id": 7,
			"data_in": 38,
			"data_out": 24,
			"can_offload": 1,
			"chosen_node_id": 4,
			"source_node_id": 2,
			"chosen_node_type": "edge",
			"input_upload_start_time": 8524.45,
			"input_upload_finish_time": 8707.78,
			"process_start_time": 8707.78,
			"process_finish_time": 8907.78,
			"output_upload_start_time": 0,
			"output_upload_finish_time": 0,
			"parents": [
				"APP_15_Inner_Layer_0:0",
				"APP_15_Inner_Layer_0:2",
				"APP_15_Inner_Layer_0:1"
			],
			"parent_upload_windows": {
				"2": [
					["8524.45", "8707.78"]
				],
				"3": [
					["8552.03", "8594.25"]
				]
			}
		},
		{
			"task_name": "APP_15_Inner_Layer_1:2",
			"total_task_id": 133,
			"application_id": 15,
			"task_id": 6,
			"data_in": 5,
			"data_out": 13,
			"can_offload": 1,
			"chosen_node_id": 3,
			"source_node_id": 2,
			"chosen_node_type": "edge",
			"input_upload_start_time": 8524.45,
			"input_upload_finish_time": 8552.03,
			"process_start_time": 8552.03,
			"process_finish_time": 9085.36,
			"output_upload_start_time": 0,
			"output_upload_finish_time": 0,
			"parents": [
				"APP_15_Inner_Layer_0:2",
				"APP_15_Inner_Layer_0:1"
			],
			"parent_upload_windows": {
				"4": [
					["8524.45", "8552.03"]
				]
			}
		},
		{
			"task_name": "APP_15_Output_Layer_0",
			"total_task_id": 135,
			"application_id": 15,
			"task_id": 8,
			"data_in": 33,
			"data_out": 12,
			"can_offload": 1,
			"chosen_node_id": 3,
			"source_node_id": 2,
			"chosen_node_type": "edge",
			"input_upload_start_time": 8908.78,
			"input_upload_finish_time": 8966.63,
			"process_start_time": 9085.36,
			"process_finish_time": 9618.69,
			"output_upload_start_time": 0,
			"output_upload_finish_time": 0,
			"parents": [
				"APP_15_Inner_Layer_1:0",
				"APP_15_Inner_Layer_1:1",
				"APP_15_Inner_Layer_1:2",
				"APP_15_Inner_Layer_1:3"
			],
			"parent_upload_windows": {
				"1": [
					["8908.78", "8966.63"]
				],
				"4": [
					["8908.78", "8942.22"]
				]
			}
		}
	],
	"edge_upload_windows": {
		"0_1": [
			[992.667, 1058.57],
			[1644.94, 1677.63],
			[4156.16, 4212.29],
			[4535.7, 4566.44],
			[4566.44, 4606.95],
			[4606.95, 4647.45],
			[4647.45, 4687.96],
			[5088.96, 5115.8]
		],
		"0_2": [
			[5612.22, 7015.56],
			[7015.56, 8391.11],
			[8391.11, 8600],
			[8600, 9308.89]
		],
		"0_3": [
			[1459.57, 1496.17],
			[4156.16, 4209.36],
			[4940.3, 4970.06],
			[5124.21, 5155.93]
		],
		"0_4": [
			[1393.9, 1453.94],
			[4115.44, 4166.69],
			[4313.44, 4339.3],
			[4535.7, 4589.88],
			[5124.21, 5180.34],
			[5714.67, 5744.44]
		],
		"1_2": [
			[8217.78, 8401.11]
		],
		"1_3": [
			[992.667, 1048.57],
			[1459.57, 1487.14],
			[1863.49, 1878.38],
			[4218.97, 4273.89],
			[4341.55, 4383.78],
			[4535.7, 4556.44],
			[5877.61, 5933.51],
			[5933.51, 5953.28],
			[6286.61, 6314.19],
			[8908.78, 8966.63]
		],
		"1_4": [
			[858.333, 876.146],
			[1343.81, 1387.99],
			[1393.9, 1443.94],
			[2330.16, 2345.04],
			[2798.83, 2837.15],
			[2925.6, 2969.78],
			[4107.12, 4134.7],
			[4535.7, 4579.88],
			[5124.21, 5166.44],
			[6279.61, 6305.24],
			[6639.57, 6674.96]
		],
		"2_3": [
			[252, 388.667],
			[2757.94, 3027.94],
			[4984.78, 5214.78],
			[7966.78, 8256.78]
		],
		"2_4": [
			[252, 388.667],
			[2757.94, 3027.94],
			[7966.78, 8256.78],
			[8524.45, 8707.78]
		],
		"3_4": [
			[523, 566.203],
			[858.333, 876.146],
			[1343.81, 1394.83],
			[2146.04, 2192.18],
			[2791.27, 2819.83],
			[3294.6, 3311.44],
			[3438.15, 3460.84],
			[4313.44, 4329.3],
			[4535.7, 4579.88],
			[4940.3, 4954.21],
			[5124.21, 5145.93],
			[5877.61, 5933.51],
			[5933.51, 5953.28],
			[6279.61, 6305.24],
			[6553.28, 6591.6],
			[6639.57, 6680.82],
			[8524.45, 8552.03],
			[8552.03, 8594.25],
			[8908.78, 8942.22]
		]
	},
	"node_types": {
		"0": "cloud",
		"1": "edge",
		"2": "mobile",
		"3": "edge",
		"4": "edge"
	}
}
