{
	"application_count": 9,
	"completed_application_count": 0,
	"total_task_count": 70,
	"finish_time": 9006,
	"completed_task_count": 6,
	"completed_tasks": [
		{
			"task_name": "APP_0_Input_Layer_0",
			"total_task_id": 0,
			"application_id": 0,
			"task_id": 0,
			"data_in": 38,
			"data_out": 28,
			"can_offload": 1,
			"chosen_node_id": 2,
			"source_node_id": 2,
			"chosen_node_type": "mobile",
			"input_upload_start_time": 0,
			"input_upload_finish_time": 0,
			"process_start_time": 1,
			"process_finish_time": 751,
			"output_upload_start_time": 0,
			"output_upload_finish_time": 0,
			"parents": [
			],
			"parent_upload_windows": {
			}
		},
		{
			"task_name": "APP_0_Inner_Layer_0:0",
			"total_task_id": 1,
			"application_id": 0,
			"task_id": 1,
			"data_in": 10,
			"data_out": 42,
			"can_offload": 1,
			"chosen_node_id": 2,
			"source_node_id": 2,
			"chosen_node_type": "mobile",
			"input_upload_start_time": 751,
			"input_upload_finish_time": 0,
			"process_start_time": 752,
			"process_finish_time": 1502,
			"output_upload_start_time": 0,
			"output_upload_finish_time": 0,
			"parents": [
				"APP_0_Input_Layer_0"
			],
			"parent_upload_windows": {
			}
		},
		{
			"task_name": "APP_0_Inner_Layer_0:1",
			"total_task_id": 2,
			"application_id": 0,
			"task_id": 2,
			"data_in": 45,
			"data_out": 16,
			"can_offload": 1,
			"chosen_node_id": 2,
			"source_node_id": 2,
			"chosen_node_type": "mobile",
			"input_upload_start_time": 751,
			"input_upload_finish_time": 0,
			"process_start_time": 1503,
			"process_finish_time": 2753,
			"output_upload_start_time": 0,
			"output_upload_finish_time": 0,
			"parents": [
				"APP_0_Input_Layer_0"
			],
			"parent_upload_windows": {
			}
		},
		{
			"task_name": "APP_0_Inner_Layer_1:1",
			"total_task_id": 4,
			"application_id": 0,
			"task_id": 4,
			"data_in": 45,
			"data_out": 40,
			"can_offload": 1,
			"chosen_node_id": 2,
			"source_node_id": 2,
			"chosen_node_type": "mobile",
			"input_upload_start_time": 2753,
			"input_upload_finish_time": 0,
			"process_start_time": 2754,
			"process_finish_time": 5004,
			"output_upload_start_time": 0,
			"output_upload_finish_time": 0,
			"parents": [
				"APP_0_Inner_Layer_0:0",
				"APP_0_Inner_Layer_0:1"
			],
			"parent_upload_windows": {
			}
		},
		{
			"task_name": "APP_0_Inner_Layer_1:0",
			"total_task_id": 3,
			"application_id": 0,
			"task_id": 3,
			"data_in": 19,
			"data_out": 49,
			"can_offload": 0,
			"chosen_node_id": 2,
			"source_node_id": 2,
			"chosen_node_type": "mobile",
			"input_upload_start_time": 2753,
			"input_upload_finish_time": 0,
			"process_start_time": 5005,
			"process_finish_time": 7255,
			"output_upload_start_time": 0,
			"output_upload_finish_time": 0,
			"parents": [
				"APP_0_Inner_Layer_0:1"
			],
			"parent_upload_windows": {
			}
		},
		{
			"task_name": "APP_0_Inner_Layer_1:2",
			"total_task_id": 5,
			"application_id": 0,
			"task_id": 5,
			"data_in": 29,
			"data_out": 23,
			"can_offload": 0,
			"chosen_node_id": 2,
			"source_node_id": 2,
			"chosen_node_type": "mobile",
			"input_upload_start_time": 2753,
			"input_upload_finish_time": 0,
			"process_start_time": 7256,
			"process_finish_time": 9006,
			"output_upload_start_time": 0,
			"output_upload_finish_time": 0,
			"parents": [
				"APP_0_Inner_Layer_0:1"
			],
			"parent_upload_windows": {
			}
		}
	],
	"edge_upload_windows": {
		"0_1": [
		],
		"0_2": [
			[10258, 10855.8],
			[10855.8, 11453.6],
			[11453.6, 12051.3],
			[12051.3, 12649.1]
		],
		"0_3": [
		],
		"0_4": [
		],
		"1_2": [
		],
		"1_3": [
		],
		"1_4": [
		],
		"2_3": [
		],
		"2_4": [
		],
		"3_4": [
		]
	},
	"node_types": {
		"0": "cloud",
		"1": "edge",
		"2": "mobile",
		"3": "edge",
		"4": "edge"
	}
}
